[{"CITY": "Cambridge", "STABBR": "MA", "ADM_RATE": "NULL", "ZIP": "02141-1805", "HIGHDEG": "4", "LOCALE": "12", "PROGRAMS": [], "SAT_AVG": "NULL", "LONGITUDE": "-71.070721", "INSTNM": "Hult International Business School", "LATITUDE": "42.36988", "CCSIZSET": "18", "INSTURL": "www.hult.edu"}, {"CITY": "Boston", "STABBR": "MA", "ADM_RATE": "NULL", "ZIP": "02110", "HIGHDEG": "4", "LOCALE": "11", "PROGRAMS": [], "SAT_AVG": "NULL", "LONGITUDE": "-71.056671", "INSTNM": "New England College of Business and Finance", "LATITUDE": "42.353619", "CCSIZSET": "6", "INSTURL": "www.necb.edu/"}, {"CITY": "Springfield", "STABBR": "MA", "ADM_RATE": "0.6316", "ZIP": "01109", "HIGHDEG": "4", "LOCALE": "12", "PROGRAMS": ["CIP42BACHL", "CIP09BACHL", "CIP44BACHL", "CIP31BACHL", "CIP23BACHL", "CIP40BACHL", "CIP43BACHL", "CIP52ASSOC", "CIP24ASSOC", "CIP16BACHL", "CIP50BACHL", "CIP45BACHL", "CIP24BACHL", "CIP51BACHL", "CIP26BACHL", "CIP54BACHL", "CIP52BACHL", "CIP30BACHL"], "SAT_AVG": "887", "LONGITUDE": "-72.558507", "INSTNM": "American International College", "LATITUDE": "42.112708", "CCSIZSET": "10", "INSTURL": "www.aic.edu"}, {"CITY": "Amherst", "STABBR": "MA", "ADM_RATE": "0.1412", "ZIP": "01002-5000", "HIGHDEG": "3", "LOCALE": "21", "PROGRAMS": ["CIP42BACHL", "CIP03BACHL", "CIP23BACHL", "CIP40BACHL", "CIP22BACHL", "CIP27BACHL", "CIP16BACHL", "CIP11BACHL", "CIP50BACHL", "CIP38BACHL", "CIP45BACHL", "CIP04BACHL", "CIP26BACHL", "CIP54BACHL", "CIP05BACHL", "CIP30BACHL"], "SAT_AVG": "1451", "LONGITUDE": "-72.518493", "INSTNM": "Amherst College", "LATITUDE": "42.372459", "CCSIZSET": "11", "INSTURL": "www.amherst.edu"}, {"CITY": "Newton Centre", "STABBR": "MA", "ADM_RATE": "NULL", "ZIP": "02459-2243", "HIGHDEG": "4", "LOCALE": "13", "PROGRAMS": [], "SAT_AVG": "NULL", "LONGITUDE": "-71.189586", "INSTNM": "Andover Newton Theological School", "LATITUDE": "42.324729", "CCSIZSET": "18", "INSTURL": "www.ants.edu"}, {"CITY": "Paxton", "STABBR": "MA", "ADM_RATE": "0.8006", "ZIP": "01612-1198", "HIGHDEG": "4", "LOCALE": "41", "PROGRAMS": ["CIP42BACHL", "CIP09BACHL", "CIP03BACHL", "CIP44BACHL", "CIP23BACHL", "CIP51CERT1", "CIP22BACHL", "CIP50BACHL", "CIP38BACHL", "CIP13BACHL", "CIP45BACHL", "CIP24BACHL", "CIP54BACHL", "CIP52BACHL", "CIP39BACHL"], "SAT_AVG": "NULL", "LONGITUDE": "-71.918961", "INSTNM": "Anna Maria College", "LATITUDE": "42.33055", "CCSIZSET": "10", "INSTURL": "www.annamaria.edu"}, {"CITY": "Marlborough", "STABBR": "MA", "ADM_RATE": "0.84", "ZIP": "01752", "HIGHDEG": "1", "LOCALE": "21", "PROGRAMS": ["CIP51CERT2"], "SAT_AVG": "NULL", "LONGITUDE": "-71.564771", "INSTNM": "Assabet Valley Regional Technical School", "LATITUDE": "42.36838", "CCSIZSET": "-2", "INSTURL": "www.assabet.org"}, {"CITY": "Worcester", "STABBR": "MA", "ADM_RATE": "0.7575", "ZIP": "01609-1296", "HIGHDEG": "4", "LOCALE": "12", "PROGRAMS": ["CIP24CERT1", "CIP42BACHL", "CIP09BACHL", "CIP03BACHL", "CIP44BACHL", "CIP23BACHL", "CIP40BACHL", "CIP51CERT1", "CIP50CERT1", "CIP22CERT1", "CIP27BACHL", "CIP16BACHL", "CIP43CERT1", "CIP11BACHL", "CIP50BACHL", "CIP09CERT1", "CIP38BACHL", "CIP13BACHL", "CIP26BACHL", "CIP54BACHL", "CIP52CERT1", "CIP05BACHL", "CIP30BACHL", "CIP39BACHL"], "SAT_AVG": "NULL", "LONGITUDE": "-71.828387", "INSTNM": "Assumption College", "LATITUDE": "42.295435", "CCSIZSET": "11", "INSTURL": "www.assumption.edu"}, {"CITY": "Wellesley", "STABBR": "MA", "ADM_RATE": "0.263", "ZIP": "02457-0310", "HIGHDEG": "4", "LOCALE": "21", "PROGRAMS": ["CIP52BACHL"], "SAT_AVG": "1317", "LONGITUDE": "-71.269479", "INSTNM": "Babson College", "LATITUDE": "42.296529", "CCSIZSET": "11", "INSTURL": "www.babson.edu"}, {"CITY": "Worcester", "STABBR": "MA", "ADM_RATE": "NULL", "ZIP": "01604", "HIGHDEG": "1", "LOCALE": "12", "PROGRAMS": ["CIP51CERT1"], "SAT_AVG": "NULL", "LONGITUDE": "-71.778773", "INSTNM": "Bancroft School of Massage Therapy", "LATITUDE": "42.26931", "CCSIZSET": "-2", "INSTURL": "https://www.bancroftsmt.com"}, {"CITY": "Boston", "STABBR": "MA", "ADM_RATE": "0.9231", "ZIP": "02136-4030", "HIGHDEG": "3", "LOCALE": "11", "PROGRAMS": ["CIP39CERT2", "CIP39ASSOC", "CIP39BACHL"], "SAT_AVG": "943", "LONGITUDE": "-71.1103", "INSTNM": "Boston Baptist College", "LATITUDE": "42.254037", "CCSIZSET": "8", "INSTURL": "Boston.edu"}, {"CITY": "Longmeadow", "STABBR": "MA", "ADM_RATE": "0.7726", "ZIP": "01106", "HIGHDEG": "4", "LOCALE": "21", "PROGRAMS": ["CIP22BACHL", "CIP22CERT1", "CIP22ASSOC", "CIP13BACHL", "CIP26BACHL", "CIP30BACHL"], "SAT_AVG": "NULL", "LONGITUDE": "-72.583974", "INSTNM": "Bay Path University", "LATITUDE": "42.055364", "CCSIZSET": "11", "INSTURL": "www.baypath.edu"}, {"CITY": "Boston", "STABBR": "MA", "ADM_RATE": "NULL", "ZIP": "02116", "HIGHDEG": "3", "LOCALE": "11", "PROGRAMS": ["CIP13ASSOC", "CIP10BACHL", "CIP51ASSOC", "CIP50ASSOC", "CIP50BACHL", "CIP10ASSOC"], "SAT_AVG": "NULL", "LONGITUDE": "-71.076956", "INSTNM": "Bay State College", "LATITUDE": "42.351965", "CCSIZSET": "6", "INSTURL": "www.baystate.edu"}, {"CITY": "Canton", "STABBR": "MA", "ADM_RATE": "NULL", "ZIP": "02021-2358", "HIGHDEG": "1", "LOCALE": "21", "PROGRAMS": ["CIP15CERT2", "CIP47CERT1", "CIP47CERT2"], "SAT_AVG": "NULL", "LONGITUDE": "-71.113455", "INSTNM": "Bay State School of Technology", "LATITUDE": "42.179506", "CCSIZSET": "-2", "INSTURL": "www.baystatetech.org"}, {"CITY": "Worcester", "STABBR": "MA", "ADM_RATE": "0.6689", "ZIP": "01609-2165", "HIGHDEG": "3", "LOCALE": "12", "PROGRAMS": ["CIP13ASSOC", "CIP42BACHL", "CIP09BACHL", "CIP31BACHL", "CIP10BACHL", "CIP51ASSOC", "CIP22BACHL", "CIP43BACHL", "CIP11BACHL", "CIP50BACHL", "CIP13BACHL", "CIP24BACHL", "CIP01BACHL", "CIP51BACHL", "CIP26BACHL", "CIP01ASSOC"], "SAT_AVG": "1009", "LONGITUDE": "-71.811895", "INSTNM": "Becker College", "LATITUDE": "42.26918", "CCSIZSET": "10", "INSTURL": "www.becker.edu"}, {"CITY": "Waltham", "STABBR": "MA", "ADM_RATE": "0.4232", "ZIP": "02452-4705", "HIGHDEG": "4", "LOCALE": "13", "PROGRAMS": ["CIP09BACHL", "CIP44BACHL", "CIP23BACHL", "CIP22BACHL", "CIP27BACHL", "CIP52ASSOC", "CIP16BACHL", "CIP11BACHL", "CIP38BACHL", "CIP24BACHL", "CIP51BACHL", "CIP54BACHL", "CIP52BACHL", "CIP30BACHL"], "SAT_AVG": "1244", "LONGITUDE": "-71.220148", "INSTNM": "Bentley University", "LATITUDE": "42.388798", "CCSIZSET": "14", "INSTURL": "www.bentley.edu"}, {"CITY": "Boston", "STABBR": "MA", "ADM_RATE": "0.2881", "ZIP": "02215", "HIGHDEG": "4", "LOCALE": "11", "PROGRAMS": ["CIP13BACHL", "CIP51BACHL"], "SAT_AVG": "NULL", "LONGITUDE": "-71.08703", "INSTNM": "Berklee College of Music", "LATITUDE": "42.346895", "CCSIZSET": "12", "INSTURL": "www.berklee.edu"}, {"CITY": "Pittsfield", "STABBR": "MA", "ADM_RATE": "NULL", "ZIP": "01201-5786", "HIGHDEG": "2", "LOCALE": "41", "PROGRAMS": ["CIP13ASSOC", "CIP14ASSOC", "CIP11CERT1", "CIP15CERT1", "CIP11ASSOC", "CIP51ASSOC", "CIP13CERT1", "CIP51CERT2", "CIP51CERT1", "CIP50CERT1", "CIP43ASSOC", "CIP31CERT1", "CIP15ASSOC", "CIP52ASSOC", "CIP24ASSOC", "CIP50ASSOC", "CIP12CERT1", "CIP03ASSOC", "CIP52CERT1", "CIP44ASSOC"], "SAT_AVG": "NULL", "LONGITUDE": "-73.318843", "INSTNM": "Berkshire Community College", "LATITUDE": "42.460877", "CCSIZSET": "2", "INSTURL": "www.berkshirecc.edu"}, {"CITY": "Boston", "STABBR": "MA", "ADM_RATE": "NULL", "ZIP": "02111", "HIGHDEG": "1", "LOCALE": "11", "PROGRAMS": ["CIP12CERT2"], "SAT_AVG": "NULL", "LONGITUDE": "-71.062529", "INSTNM": "Empire Beauty School-Boston", "LATITUDE": "42.354744", "CCSIZSET": "-2", "INSTURL": "www.empire.edu"}, {"CITY": "Boston", "STABBR": "MA", "ADM_RATE": "NULL", "ZIP": "02115-2703", "HIGHDEG": "4", "LOCALE": "11", "PROGRAMS": ["CIP04BACHL", "CIP04CERT1"], "SAT_AVG": "NULL", "LONGITUDE": "-71.085851", "INSTNM": "Boston Architectural College", "LATITUDE": "42.34867", "CCSIZSET": "6", "INSTURL": "www.the-bac.edu"}, {"CITY": "Brookline", "STABBR": "MA", "ADM_RATE": "NULL", "ZIP": "02446", "HIGHDEG": "4", "LOCALE": "21", "PROGRAMS": [], "SAT_AVG": "NULL", "LONGITUDE": "-71.133025", "INSTNM": "Boston Graduate School of Psychoanalysis Inc", "LATITUDE": "42.339481", "CCSIZSET": "18", "INSTURL": "www.bgsp.edu/"}, {"CITY": "Chestnut Hill", "STABBR": "MA", "ADM_RATE": "0.2851", "ZIP": "02467", "HIGHDEG": "4", "LOCALE": "13", "PROGRAMS": ["CIP42BACHL", "CIP09BACHL", "CIP03BACHL", "CIP23BACHL", "CIP40BACHL", "CIP27BACHL", "CIP16BACHL", "CIP11BACHL", "CIP50BACHL", "CIP38BACHL", "CIP13BACHL", "CIP45BACHL", "CIP51BACHL", "CIP26BACHL", "CIP54BACHL", "CIP52BACHL", "CIP05BACHL", "CIP30BACHL", "CIP39BACHL"], "SAT_AVG": "1380", "LONGITUDE": "-71.171488", "INSTNM": "Boston College", "LATITUDE": "42.337688", "CCSIZSET": "17", "INSTURL": "www.bc.edu"}, {"CITY": "Boston", "STABBR": "MA", "ADM_RATE": "0.4584", "ZIP": "02215", "HIGHDEG": "4", "LOCALE": "11", "PROGRAMS": ["CIP50BACHL"], "SAT_AVG": "NULL", "LONGITUDE": "-71.090502", "INSTNM": "The Boston Conservatory", "LATITUDE": "42.346933", "CCSIZSET": "7", "INSTURL": "www.bostonconservatory.edu"}, {"CITY": "Boston", "STABBR": "MA", "ADM_RATE": "0.3262", "ZIP": "02215", "HIGHDEG": "4", "LOCALE": "11", "PROGRAMS": ["CIP39CERT4", "CIP42BACHL", "CIP09BACHL", "CIP45CERT2", "CIP30CERT4", "CIP11CERT2", "CIP15CERT2", "CIP23BACHL", "CIP13CERT2", "CIP40BACHL", "CIP51CERT4", "CIP14CERT2", "CIP51CERT2", "CIP50CERT1", "CIP50CERT2", "CIP22BACHL", "CIP43BACHL", "CIP27BACHL", "CIP16BACHL", "CIP43CERT2", "CIP11BACHL", "CIP50BACHL", "CIP23CERT2", "CIP38BACHL", "CIP13BACHL", "CIP45BACHL", "CIP14BACHL", "CIP24BACHL", "CIP04BACHL", "CIP26CERT1", "CIP26CERT2", "CIP51BACHL", "CIP26BACHL", "CIP54BACHL", "CIP52BACHL", "CIP44CERT2", "CIP44CERT4", "CIP05CERT4", "CIP05CERT2", "CIP52CERT2", "CIP52CERT1", "CIP26CERT4", "CIP05BACHL", "CIP30BACHL"], "SAT_AVG": "1303", "LONGITUDE": "-71.09984", "INSTNM": "Boston University", "LATITUDE": "42.349581", "CCSIZSET": "17", "INSTURL": "www.bu.edu"}, {"CITY": "Waltham", "STABBR": "MA", "ADM_RATE": "0.3402", "ZIP": "02454-9110", "HIGHDEG": "4", "LOCALE": "13", "PROGRAMS": ["CIP42BACHL", "CIP03BACHL", "CIP44BACHL", "CIP23BACHL", "CIP40BACHL", "CIP27BACHL", "CIP16BACHL", "CIP11BACHL", "CIP50BACHL", "CIP38BACHL", "CIP13BACHL", "CIP45BACHL", "CIP26BACHL", "CIP54BACHL", "CIP52BACHL", "CIP05BACHL", "CIP30BACHL"], "SAT_AVG": "1360", "LONGITUDE": "-71.254716", "INSTNM": "Brandeis University", "LATITUDE": "42.364947", "CCSIZSET": "14", "INSTURL": "www.brandeis.edu/"}, {"CITY": "Bridgewater", "STABBR": "MA", "ADM_RATE": "0.8071", "ZIP": "02325", "HIGHDEG": "4", "LOCALE": "21", "PROGRAMS": ["CIP42BACHL", "CIP09BACHL", "CIP44BACHL", "CIP23BACHL", "CIP13CERT1", "CIP40BACHL", "CIP43BACHL", "CIP27BACHL", "CIP16BACHL", "CIP11BACHL", "CIP50BACHL", "CIP38BACHL", "CIP13BACHL", "CIP45BACHL", "CIP51BACHL", "CIP26BACHL", "CIP49BACHL", "CIP54BACHL", "CIP52BACHL", "CIP05CERT1", "CIP52CERT1"], "SAT_AVG": "996", "LONGITUDE": "-70.966058", "INSTNM": "Bridgewater State University", "LATITUDE": "41.987785", "CCSIZSET": "13", "INSTURL": "www.bridgew.edu"}, {"CITY": "Fall River", "STABBR": "MA", "ADM_RATE": "NULL", "ZIP": "02720-7395", "HIGHDEG": "2", "LOCALE": "21", "PROGRAMS": ["CIP13ASSOC", "CIP14ASSOC", "CIP30CERT1", "CIP15CERT1", "CIP51ASSOC", "CIP13CERT1", "CIP14CERT1", "CIP50CERT1", "CIP43ASSOC", "CIP22CERT1", "CIP15ASSOC", "CIP52ASSOC", "CIP43CERT1", "CIP50ASSOC", "CIP22ASSOC", "CIP26CERT1", "CIP16ASSOC", "CIP09ASSOC", "CIP16CERT1", "CIP12CERT1", "CIP01CERT1", "CIP52CERT1", "CIP12ASSOC", "CIP19CERT1", "CIP44ASSOC", "CIP48CERT1"], "SAT_AVG": "NULL", "LONGITUDE": "-71.120263", "INSTNM": "Bristol Community College", "LATITUDE": "41.721337", "CCSIZSET": "4", "INSTURL": "www.bristolcc.edu"}, {"CITY": "Brockton", "STABBR": "MA", "ADM_RATE": "0.6667", "ZIP": "02302-1905", "HIGHDEG": "1", "LOCALE": "21", "PROGRAMS": ["CIP51CERT4"], "SAT_AVG": "NULL", "LONGITUDE": "-70.991415", "INSTNM": "Signature Healthcare Brockton Hospital School of Nursing", "LATITUDE": "42.08736", "CCSIZSET": "-2", "INSTURL": "www.bhson.org"}, {"CITY": "Boston", "STABBR": "MA", "ADM_RATE": "NULL", "ZIP": "02129-2925", "HIGHDEG": "2", "LOCALE": "11", "PROGRAMS": ["CIP13ASSOC", "CIP14ASSOC", "CIP11CERT1", "CIP15CERT1", "CIP11ASSOC", "CIP51ASSOC", "CIP13CERT1", "CIP51CERT1", "CIP40ASSOC", "CIP22CERT1", "CIP43CERT1", "CIP27ASSOC", "CIP50ASSOC", "CIP22ASSOC", "CIP26ASSOC", "CIP16ASSOC", "CIP12CERT1", "CIP44CERT1", "CIP52CERT1", "CIP12ASSOC", "CIP47ASSOC", "CIP44ASSOC"], "SAT_AVG": "NULL", "LONGITUDE": "-71.069263", "INSTNM": "Bunker Hill Community College", "LATITUDE": "42.374806", "CCSIZSET": "4", "INSTURL": "www.bhcc.mass.edu"}, {"CITY": "Cambridge", "STABBR": "MA", "ADM_RATE": "NULL", "ZIP": "02138", "HIGHDEG": "4", "LOCALE": "12", "PROGRAMS": ["CIP42BACHL", "CIP44BACHL", "CIP51CERT1", "CIP52BACHL", "CIP30BACHL"], "SAT_AVG": "NULL", "LONGITUDE": "-71.11084", "INSTNM": "Cambridge College", "LATITUDE": "42.369193", "CCSIZSET": "9", "INSTURL": "www.cambridgecollege.edu"}, {"CITY": "West Barnstable", "STABBR": "MA", "ADM_RATE": "NULL", "ZIP": "02668-1599", "HIGHDEG": "2", "LOCALE": "13", "PROGRAMS": ["CIP13ASSOC", "CIP30ASSOC", "CIP14ASSOC", "CIP11CERT1", "CIP15CERT1", "CIP11ASSOC", "CIP51ASSOC", "CIP13CERT1", "CIP45CERT1", "CIP10CERT1", "CIP14CERT1", "CIP51CERT1", "CIP50CERT1", "CIP43ASSOC", "CIP22CERT1", "CIP15ASSOC", "CIP52ASSOC", "CIP24ASSOC", "CIP43CERT1", "CIP50ASSOC", "CIP47CERT1", "CIP38ASSOC", "CIP54ASSOC", "CIP16ASSOC", "CIP09ASSOC", "CIP42ASSOC", "CIP16CERT1", "CIP12CERT1", "CIP03ASSOC", "CIP23ASSOC", "CIP44CERT1", "CIP01CERT1", "CIP52CERT1", "CIP47ASSOC", "CIP03CERT1", "CIP45ASSOC", "CIP44ASSOC"], "SAT_AVG": "NULL", "LONGITUDE": "-70.337334", "INSTNM": "Cape Cod Community College", "LATITUDE": "41.69192", "CCSIZSET": "3", "INSTURL": "www.capecod.edu"}, {"CITY": "Woburn", "STABBR": "MA", "ADM_RATE": "NULL", "ZIP": "01801-6819", "HIGHDEG": "1", "LOCALE": "21", "PROGRAMS": ["CIP12CERT2", "CIP12CERT1"], "SAT_AVG": "NULL", "LONGITUDE": "-71.1371", "INSTNM": "Catherine Hinds Institute of Esthetics", "LATITUDE": "42.492682", "CCSIZSET": "-2", "INSTURL": "www.catherinehinds.edu"}, {"CITY": "Milton", "STABBR": "MA", "ADM_RATE": "0.5238", "ZIP": "02186", "HIGHDEG": "3", "LOCALE": "21", "PROGRAMS": ["CIP51ASSOC", "CIP51CERT2", "CIP51CERT1", "CIP51BACHL"], "SAT_AVG": "NULL", "LONGITUDE": "-71.058559", "INSTNM": "Laboure College", "LATITUDE": "42.261615", "CCSIZSET": "6", "INSTURL": "www.laboure.edu/about-labour-"}, {"CITY": "Worcester", "STABBR": "MA", "ADM_RATE": "0.5507", "ZIP": "01610-1477", "HIGHDEG": "4", "LOCALE": "12", "PROGRAMS": ["CIP42BACHL", "CIP09BACHL", "CIP03BACHL", "CIP44BACHL", "CIP23BACHL", "CIP40BACHL", "CIP43BACHL", "CIP27BACHL", "CIP16BACHL", "CIP11BACHL", "CIP50BACHL", "CIP38BACHL", "CIP45BACHL", "CIP24BACHL", "CIP26BACHL", "CIP54BACHL", "CIP52BACHL", "CIP44CERT1", "CIP05BACHL", "CIP30BACHL"], "SAT_AVG": "NULL", "LONGITUDE": "-71.823537", "INSTNM": "Clark University", "LATITUDE": "42.251064", "CCSIZSET": "14", "INSTURL": "www.clarku.edu"}, {"CITY": "Conway", "STABBR": "MA", "ADM_RATE": "NULL", "ZIP": "01341-0179", "HIGHDEG": "4", "LOCALE": "41", "PROGRAMS": [], "SAT_AVG": "NULL", "LONGITUDE": "-72.686919", "INSTNM": "Conway School of Landscape Design", "LATITUDE": "42.506313", "CCSIZSET": "18", "INSTURL": "www.csld.edu"}, {"CITY": "Milton", "STABBR": "MA", "ADM_RATE": "0.877", "ZIP": "02186-2395", "HIGHDEG": "4", "LOCALE": "21", "PROGRAMS": ["CIP42BACHL", "CIP09BACHL", "CIP03BACHL", "CIP23BACHL", "CIP43BACHL", "CIP11BACHL", "CIP50BACHL", "CIP38BACHL", "CIP13BACHL", "CIP45BACHL", "CIP24BACHL", "CIP51BACHL", "CIP26BACHL", "CIP52BACHL", "CIP30BACHL"], "SAT_AVG": "941", "LONGITUDE": "-71.114007", "INSTNM": "Curry College", "LATITUDE": "42.240616", "CCSIZSET": "10", "INSTURL": "https://www.curry.edu"}, {"CITY": "Somerville", "STABBR": "MA", "ADM_RATE": "NULL", "ZIP": "02145", "HIGHDEG": "1", "LOCALE": "21", "PROGRAMS": ["CIP11CERT2", "CIP51CERT2", "CIP51CERT1", "CIP43CERT2"], "SAT_AVG": "NULL", "LONGITUDE": "-71.082106", "INSTNM": "Lincoln Technical Institute-Somerville", "LATITUDE": "42.391693", "CCSIZSET": "-2", "INSTURL": "www.lincolnedu.com/campus/somerville-ma"}, {"CITY": "Franklin", "STABBR": "MA", "ADM_RATE": "0.6736", "ZIP": "02038-1941", "HIGHDEG": "3", "LOCALE": "21", "PROGRAMS": ["CIP13ASSOC", "CIP51ASSOC", "CIP31ASSOC", "CIP43ASSOC", "CIP52ASSOC", "CIP24ASSOC", "CIP50ASSOC", "CIP50BACHL", "CIP24BACHL", "CIP54ASSOC", "CIP26ASSOC", "CIP09ASSOC", "CIP42ASSOC", "CIP52BACHL"], "SAT_AVG": "NULL", "LONGITUDE": "-71.399003", "INSTNM": "Dean College", "LATITUDE": "42.08497", "CCSIZSET": "11", "INSTURL": "www.dean.edu"}, {"CITY": "Fall River", "STABBR": "MA", "ADM_RATE": "0.3409", "ZIP": "02723", "HIGHDEG": "1", "LOCALE": "21", "PROGRAMS": ["CIP51CERT2"], "SAT_AVG": "NULL", "LONGITUDE": "-71.1315", "INSTNM": "Diman Regional Technical Institute", "LATITUDE": "41.6918", "CCSIZSET": "-2", "INSTURL": "dimanregional.org"}, {"CITY": "Concord", "STABBR": "MA", "ADM_RATE": "NULL", "ZIP": "01742", "HIGHDEG": "1", "LOCALE": "21", "PROGRAMS": ["CIP47CERT4"], "SAT_AVG": "NULL", "LONGITUDE": "-71.290245", "INSTNM": "National Aviation Academy of New England", "LATITUDE": "42.461992", "CCSIZSET": "-2", "INSTURL": "www.naa.edu"}, {"CITY": "Quincy", "STABBR": "MA", "ADM_RATE": "0.6129", "ZIP": "02170-2999", "HIGHDEG": "4", "LOCALE": "21", "PROGRAMS": ["CIP13ASSOC", "CIP42BACHL", "CIP09BACHL", "CIP03BACHL", "CIP44BACHL", "CIP31BACHL", "CIP23BACHL", "CIP40BACHL", "CIP43BACHL", "CIP27BACHL", "CIP52ASSOC", "CIP24ASSOC", "CIP11BACHL", "CIP50BACHL", "CIP38BACHL", "CIP13BACHL", "CIP14BACHL", "CIP24BACHL", "CIP51BACHL", "CIP26BACHL", "CIP54BACHL", "CIP39ASSOC", "CIP52BACHL", "CIP39BACHL"], "SAT_AVG": "978", "LONGITUDE": "-71.011238", "INSTNM": "Eastern Nazarene College", "LATITUDE": "42.271214", "CCSIZSET": "11", "INSTURL": "www.enc.edu"}, {"CITY": "Boston", "STABBR": "MA", "ADM_RATE": "0.4903", "ZIP": "02116-4624", "HIGHDEG": "4", "LOCALE": "11", "PROGRAMS": ["CIP09BACHL", "CIP23BACHL", "CIP10BACHL", "CIP50BACHL", "CIP13BACHL", "CIP51BACHL", "CIP52BACHL", "CIP30BACHL"], "SAT_AVG": "1211", "LONGITUDE": "-71.074037", "INSTNM": "Emerson College", "LATITUDE": "42.35532", "CCSIZSET": "14", "INSTURL": "www.emerson.edu"}, {"CITY": "Boston", "STABBR": "MA", "ADM_RATE": "0.7841", "ZIP": "02115", "HIGHDEG": "4", "LOCALE": "11", "PROGRAMS": ["CIP42BACHL", "CIP09BACHL", "CIP44BACHL", "CIP23BACHL", "CIP40BACHL", "CIP27BACHL", "CIP16BACHL", "CIP50BACHL", "CIP38BACHL", "CIP13BACHL", "CIP45BACHL", "CIP24BACHL", "CIP51BACHL", "CIP26BACHL", "CIP54BACHL", "CIP52BACHL", "CIP05BACHL", "CIP30BACHL"], "SAT_AVG": "NULL", "LONGITUDE": "-71.103038", "INSTNM": "Emmanuel College", "LATITUDE": "42.341191", "CCSIZSET": "11", "INSTURL": "www.emmanuel.edu"}, {"CITY": "Beverly", "STABBR": "MA", "ADM_RATE": "0.7278", "ZIP": "01915", "HIGHDEG": "4", "LOCALE": "21", "PROGRAMS": ["CIP09BACHL", "CIP03BACHL", "CIP44BACHL", "CIP31BACHL", "CIP23BACHL", "CIP13CERT1", "CIP43BACHL", "CIP11BACHL", "CIP50BACHL", "CIP13BACHL", "CIP45BACHL", "CIP51BACHL", "CIP26BACHL", "CIP54BACHL", "CIP30BACHL"], "SAT_AVG": "NULL", "LONGITUDE": "-70.840729", "INSTNM": "Endicott College", "LATITUDE": "42.554177", "CCSIZSET": "14", "INSTURL": "www.endicott.edu"}, {"CITY": "Cambridge", "STABBR": "MA", "ADM_RATE": "NULL", "ZIP": "02138-3494", "HIGHDEG": "4", "LOCALE": "12", "PROGRAMS": [], "SAT_AVG": "NULL", "LONGITUDE": "-71.125518", "INSTNM": "Episcopal Divinity School", "LATITUDE": "42.376558", "CCSIZSET": "18", "INSTURL": "www.eds.edu"}, {"CITY": "Fall River", "STABBR": "MA", "ADM_RATE": "NULL", "ZIP": "02720-3445", "HIGHDEG": "1", "LOCALE": "21", "PROGRAMS": ["CIP12CERT2", "CIP12CERT1"], "SAT_AVG": "NULL", "LONGITUDE": "-71.157929", "INSTNM": "Rob Roy Academy-Fall River", "LATITUDE": "41.698797", "CCSIZSET": "-2", "INSTURL": "www.rob-roy.com"}, {"CITY": "Boston", "STABBR": "MA", "ADM_RATE": "0.7018", "ZIP": "02116", "HIGHDEG": "3", "LOCALE": "11", "PROGRAMS": ["CIP31BACHL", "CIP11ASSOC", "CIP15ASSOC", "CIP50ASSOC", "CIP22ASSOC"], "SAT_AVG": "NULL", "LONGITUDE": "-71.074125", "INSTNM": "Fisher College", "LATITUDE": "42.355253", "CCSIZSET": "9", "INSTURL": "www.fisher.edu"}, {"CITY": "Fitchburg", "STABBR": "MA", "ADM_RATE": "0.7476", "ZIP": "01420-2697", "HIGHDEG": "4", "LOCALE": "22", "PROGRAMS": ["CIP42BACHL", "CIP09BACHL", "CIP44BACHL", "CIP11CERT1", "CIP31BACHL", "CIP23BACHL", "CIP13CERT1", "CIP40BACHL", "CIP43BACHL", "CIP19BACHL", "CIP27BACHL", "CIP11BACHL", "CIP50BACHL", "CIP13BACHL", "CIP45BACHL", "CIP24BACHL", "CIP04BACHL", "CIP26BACHL", "CIP54BACHL", "CIP52BACHL", "CIP52CERT1", "CIP30BACHL", "CIP15BACHL"], "SAT_AVG": "993", "LONGITUDE": "-71.789354", "INSTNM": "Fitchburg State University", "LATITUDE": "42.589345", "CCSIZSET": "13", "INSTURL": "www.fitchburgstate.edu"}, {"CITY": "Framingham", "STABBR": "MA", "ADM_RATE": "0.7081", "ZIP": "01701-9101", "HIGHDEG": "4", "LOCALE": "13", "PROGRAMS": ["CIP42BACHL", "CIP03BACHL", "CIP23BACHL", "CIP10BACHL", "CIP40BACHL", "CIP19BACHL", "CIP27BACHL", "CIP16BACHL", "CIP11BACHL", "CIP50BACHL", "CIP13BACHL", "CIP45BACHL", "CIP24BACHL", "CIP01BACHL", "CIP51BACHL", "CIP26BACHL", "CIP54BACHL", "CIP52BACHL"], "SAT_AVG": "975", "LONGITUDE": "-71.437175", "INSTNM": "Framingham State University", "LATITUDE": "42.297289", "CCSIZSET": "14", "INSTURL": "www.framingham.edu/"}, {"CITY": "Boston", "STABBR": "MA", "ADM_RATE": "NULL", "ZIP": "02116", "HIGHDEG": "3", "LOCALE": "11", "PROGRAMS": ["CIP51ASSOC", "CIP51CERT1", "CIP46ASSOC", "CIP15ASSOC", "CIP46CERT1", "CIP47CERT1", "CIP51BACHL", "CIP47ASSOC", "CIP47BACHL"], "SAT_AVG": "NULL", "LONGITUDE": "-71.070231", "INSTNM": "Benjamin Franklin Institute of Technology", "LATITUDE": "42.346023", "CCSIZSET": "6", "INSTURL": "www.bfit.edu/"}, {"CITY": "Wenham", "STABBR": "MA", "ADM_RATE": "0.9323", "ZIP": "01984", "HIGHDEG": "4", "LOCALE": "21", "PROGRAMS": ["CIP42BACHL", "CIP09BACHL", "CIP44BACHL", "CIP31BACHL", "CIP23BACHL", "CIP40BACHL", "CIP27BACHL", "CIP16BACHL", "CIP11BACHL", "CIP50BACHL", "CIP38BACHL", "CIP13BACHL", "CIP45BACHL", "CIP26BACHL", "CIP54BACHL", "CIP52BACHL", "CIP05BACHL", "CIP30BACHL", "CIP39BACHL"], "SAT_AVG": "1112", "LONGITUDE": "-70.819133", "INSTNM": "Gordon College", "LATITUDE": "42.588173", "CCSIZSET": "11", "INSTURL": "www.gordon.edu"}, {"CITY": "South Hamilton", "STABBR": "MA", "ADM_RATE": "NULL", "ZIP": "01982", "HIGHDEG": "4", "LOCALE": "21", "PROGRAMS": [], "SAT_AVG": "NULL", "LONGITUDE": "-70.846387", "INSTNM": "Gordon-Conwell Theological Seminary", "LATITUDE": "42.613475", "CCSIZSET": "18", "INSTURL": "www.gordonconwell.edu"}, {"CITY": "Greenfield", "STABBR": "MA", "ADM_RATE": "NULL", "ZIP": "01301-9739", "HIGHDEG": "2", "LOCALE": "32", "PROGRAMS": ["CIP13ASSOC", "CIP14ASSOC", "CIP11CERT1", "CIP11ASSOC", "CIP51ASSOC", "CIP13CERT1", "CIP51CERT2", "CIP51CERT1", "CIP50CERT1", "CIP43ASSOC", "CIP31CERT2", "CIP50ASSOC", "CIP52CERT2", "CIP52CERT1", "CIP03CERT1"], "SAT_AVG": "NULL", "LONGITUDE": "-72.630978", "INSTNM": "Greenfield Community College", "LATITUDE": "42.599521", "CCSIZSET": "2", "INSTURL": "www.gcc.mass.edu"}, {"CITY": "Turners Falls", "STABBR": "MA", "ADM_RATE": "NULL", "ZIP": "01376-0308", "HIGHDEG": "1", "LOCALE": "32", "PROGRAMS": ["CIP50CERT2"], "SAT_AVG": "NULL", "LONGITUDE": "-72.529819", "INSTNM": "Hallmark Institute of Photography", "LATITUDE": "42.589389", "CCSIZSET": "-2", "INSTURL": "hallmark.edu"}, {"CITY": "Amherst", "STABBR": "MA", "ADM_RATE": "0.7001", "ZIP": "01002-5001", "HIGHDEG": "3", "LOCALE": "21", "PROGRAMS": ["CIP42BACHL", "CIP09BACHL", "CIP03BACHL", "CIP44BACHL", "CIP31BACHL", "CIP23BACHL", "CIP40BACHL", "CIP22BACHL", "CIP27BACHL", "CIP16BACHL", "CIP11BACHL", "CIP50BACHL", "CIP38BACHL", "CIP13BACHL", "CIP45BACHL", "CIP24BACHL", "CIP04BACHL", "CIP01BACHL", "CIP51BACHL", "CIP26BACHL", "CIP54BACHL", "CIP52BACHL", "CIP05BACHL", "CIP30BACHL"], "SAT_AVG": "NULL", "LONGITUDE": "-72.532401", "INSTNM": "Hampshire College", "LATITUDE": "42.324772", "CCSIZSET": "11", "INSTURL": "www.hampshire.edu"}, {"CITY": "Cambridge", "STABBR": "MA", "ADM_RATE": "0.0558", "ZIP": "02138", "HIGHDEG": "4", "LOCALE": "12", "PROGRAMS": ["CIP40BACHL", "CIP27BACHL", "CIP16BACHL", "CIP11BACHL", "CIP26BACHL", "CIP05BACHL"], "SAT_AVG": "1497", "LONGITUDE": "-71.118177", "INSTNM": "Harvard University", "LATITUDE": "42.374429", "CCSIZSET": "17", "INSTURL": "www.harvard.edu"}, {"CITY": "Newton Centre", "STABBR": "MA", "ADM_RATE": "NULL", "ZIP": "02459-2237", "HIGHDEG": "4", "LOCALE": "13", "PROGRAMS": [], "SAT_AVG": "NULL", "LONGITUDE": "-71.190525", "INSTNM": "Hebrew College", "LATITUDE": "42.3264", "CCSIZSET": "6", "INSTURL": "www.hebrewcollege.edu"}, {"CITY": "Brookline", "STABBR": "MA", "ADM_RATE": "NULL", "ZIP": "02445-7496", "HIGHDEG": "4", "LOCALE": "21", "PROGRAMS": ["CIP23BACHL", "CIP16BACHL", "CIP38BACHL", "CIP13BACHL", "CIP24BACHL", "CIP52BACHL"], "SAT_AVG": "NULL", "LONGITUDE": "-71.129418", "INSTNM": "Hellenic College-Holy Cross Greek Orthodox School of Theology", "LATITUDE": "42.317018", "CCSIZSET": "8", "INSTURL": "hchc.edu"}, {"CITY": "Worcester", "STABBR": "MA", "ADM_RATE": "0.3703", "ZIP": "01610-2395", "HIGHDEG": "3", "LOCALE": "12", "PROGRAMS": ["CIP42BACHL", "CIP23BACHL", "CIP40BACHL", "CIP27BACHL", "CIP16BACHL", "CIP50BACHL", "CIP38BACHL", "CIP45BACHL", "CIP26BACHL", "CIP54BACHL", "CIP30BACHL"], "SAT_AVG": "NULL", "LONGITUDE": "-71.808627", "INSTNM": "College of the Holy Cross", "LATITUDE": "42.238942", "CCSIZSET": "11", "INSTURL": "www.holycross.edu"}, {"CITY": "Holyoke", "STABBR": "MA", "ADM_RATE": "NULL", "ZIP": "01040", "HIGHDEG": "2", "LOCALE": "21", "PROGRAMS": ["CIP14ASSOC", "CIP30CERT1", "CIP11CERT1", "CIP11ASSOC", "CIP51ASSOC", "CIP13CERT1", "CIP51CERT2", "CIP51CERT1", "CIP50CERT1", "CIP40ASSOC", "CIP31ASSOC", "CIP31CERT1", "CIP15ASSOC", "CIP19ASSOC", "CIP27ASSOC", "CIP50ASSOC", "CIP26ASSOC", "CIP12CERT2", "CIP19CERT1", "CIP03CERT1", "CIP44ASSOC"], "SAT_AVG": "NULL", "LONGITUDE": "-72.650683", "INSTNM": "Holyoke Community College", "LATITUDE": "42.195503", "CCSIZSET": "3", "INSTURL": "www.hcc.edu"}, {"CITY": "West Springfield", "STABBR": "MA", "ADM_RATE": "NULL", "ZIP": "01089", "HIGHDEG": "1", "LOCALE": "21", "PROGRAMS": ["CIP12CERT2", "CIP12CERT1"], "SAT_AVG": "NULL", "LONGITUDE": "-72.622508", "INSTNM": "Kay Harvey Academy of Hair Design", "LATITUDE": "42.105842", "CCSIZSET": "-2", "INSTURL": "www.labarononline.com"}, {"CITY": "Brockton", "STABBR": "MA", "ADM_RATE": "NULL", "ZIP": "02301", "HIGHDEG": "1", "LOCALE": "21", "PROGRAMS": ["CIP12CERT2", "CIP12CERT1"], "SAT_AVG": "NULL", "LONGITUDE": "-71.060265", "INSTNM": "La Baron Hairdressing Academy-Brockton", "LATITUDE": "42.052591", "CCSIZSET": "-2", "INSTURL": "www.labarononline.com"}, {"CITY": "New Bedford", "STABBR": "MA", "ADM_RATE": "NULL", "ZIP": "02740", "HIGHDEG": "1", "LOCALE": "22", "PROGRAMS": ["CIP12CERT2", "CIP12CERT1"], "SAT_AVG": "NULL", "LONGITUDE": "-70.929296", "INSTNM": "La Baron Hairdressing Academy-New Bedford", "LATITUDE": "41.633881", "CCSIZSET": "-2", "INSTURL": "labarononline.com"}, {"CITY": "Newton", "STABBR": "MA", "ADM_RATE": "0.7815", "ZIP": "02466", "HIGHDEG": "4", "LOCALE": "13", "PROGRAMS": ["CIP42BACHL", "CIP09BACHL", "CIP03BACHL", "CIP44BACHL", "CIP31BACHL", "CIP23BACHL", "CIP22BACHL", "CIP27BACHL", "CIP50BACHL", "CIP13BACHL", "CIP45BACHL", "CIP24BACHL", "CIP51BACHL", "CIP54BACHL", "CIP52BACHL", "CIP30BACHL"], "SAT_AVG": "966", "LONGITUDE": "-71.243738", "INSTNM": "Lasell College", "LATITUDE": "42.342712", "CCSIZSET": "11", "INSTURL": "www.lasell.edu/"}, {"CITY": "Medford", "STABBR": "MA", "ADM_RATE": "NULL", "ZIP": "02155", "HIGHDEG": "2", "LOCALE": "21", "PROGRAMS": ["CIP51ASSOC"], "SAT_AVG": "NULL", "LONGITUDE": "-71.110848", "INSTNM": "Lawrence Memorial Hospital School of Nursing", "LATITUDE": "42.42559", "CCSIZSET": "1", "INSTURL": "www.lmregis.org"}, {"CITY": "Cambridge", "STABBR": "MA", "ADM_RATE": "0.671", "ZIP": "02138-2790", "HIGHDEG": "4", "LOCALE": "12", "PROGRAMS": ["CIP09BACHL", "CIP03BACHL", "CIP50CERT4", "CIP44BACHL", "CIP23BACHL", "CIP10BACHL", "CIP19BACHL", "CIP24ASSOC", "CIP50BACHL", "CIP13BACHL", "CIP45BACHL", "CIP24BACHL", "CIP51BACHL", "CIP26BACHL", "CIP54BACHL", "CIP30BACHL"], "SAT_AVG": "1066", "LONGITUDE": "-71.115601", "INSTNM": "Lesley University", "LATITUDE": "42.378429", "CCSIZSET": "13", "INSTURL": "www.lesley.edu"}, {"CITY": "Cambridge", "STABBR": "MA", "ADM_RATE": "0.9394", "ZIP": "02138", "HIGHDEG": "4", "LOCALE": "12", "PROGRAMS": ["CIP50CERT4"], "SAT_AVG": "NULL", "LONGITUDE": "-71.123431", "INSTNM": "Longy School of Music of Bard College", "LATITUDE": "42.37854", "CCSIZSET": "6", "INSTURL": "longy.edu"}, {"CITY": "Lowell", "STABBR": "MA", "ADM_RATE": "NULL", "ZIP": "01852-1909", "HIGHDEG": "1", "LOCALE": "21", "PROGRAMS": ["CIP12CERT2", "CIP12CERT1"], "SAT_AVG": "NULL", "LONGITUDE": "-71.308097", "INSTNM": "Lowell Academy Hairstyling Institute", "LATITUDE": "42.64368", "CCSIZSET": "-2", "INSTURL": "www.lowellacademy.com"}, {"CITY": "Lowell", "STABBR": "MA", "ADM_RATE": "0.5679", "ZIP": "01854-5104", "HIGHDEG": "4", "LOCALE": "21", "PROGRAMS": ["CIP30CERT1", "CIP40BACHL", "CIP14CERT1", "CIP16BACHL", "CIP50BACHL", "CIP38BACHL", "CIP45BACHL", "CIP14BACHL", "CIP26BACHL", "CIP54BACHL", "CIP05BACHL", "CIP30BACHL"], "SAT_AVG": "1197", "LONGITUDE": "-71.325081", "INSTNM": "University of Massachusetts-Lowell", "LATITUDE": "42.65372", "CCSIZSET": "16", "INSTURL": "www.uml.edu"}, {"CITY": "Springfield", "STABBR": "MA", "ADM_RATE": "NULL", "ZIP": "01103", "HIGHDEG": "1", "LOCALE": "12", "PROGRAMS": ["CIP12CERT2", "CIP12CERT1"], "SAT_AVG": "NULL", "LONGITUDE": "-72.59147", "INSTNM": "Mansfield Beauty Schools-Springfield", "LATITUDE": "42.10372", "CCSIZSET": "-2", "INSTURL": "mansfieldbeautyschools.edu"}, {"CITY": "Quincy", "STABBR": "MA", "ADM_RATE": "NULL", "ZIP": "02169", "HIGHDEG": "1", "LOCALE": "21", "PROGRAMS": ["CIP12CERT2", "CIP12CERT1"], "SAT_AVG": "NULL", "LONGITUDE": "-71.003196", "INSTNM": "Mansfield Beauty Schools-Quincy", "LATITUDE": "42.245188", "CCSIZSET": "-2", "INSTURL": "www.mansfieldbeautyschools.edu"}, {"CITY": "Amherst", "STABBR": "MA", "ADM_RATE": "0.5832", "ZIP": "01003", "HIGHDEG": "4", "LOCALE": "21", "PROGRAMS": ["CIP42BACHL", "CIP03BACHL", "CIP40CERT1", "CIP30CERT1", "CIP31BACHL", "CIP23BACHL", "CIP46BACHL", "CIP45CERT1", "CIP40BACHL", "CIP22BACHL", "CIP54CERT1", "CIP38CERT1", "CIP27BACHL", "CIP16BACHL", "CIP11BACHL", "CIP50BACHL", "CIP38BACHL", "CIP13BACHL", "CIP45BACHL", "CIP14BACHL", "CIP24BACHL", "CIP04BACHL", "CIP26CERT1", "CIP16CERT1", "CIP01BACHL", "CIP26BACHL", "CIP54BACHL", "CIP01ASSOC", "CIP44CERT1", "CIP05CERT1", "CIP05BACHL"], "SAT_AVG": "1226", "LONGITUDE": "-72.52617", "INSTNM": "University of Massachusetts-Amherst", "LATITUDE": "42.386162", "CCSIZSET": "17", "INSTURL": "www.umass.edu"}, {"CITY": "Boston", "STABBR": "MA", "ADM_RATE": "0.6905", "ZIP": "02125-3393", "HIGHDEG": "4", "LOCALE": "11", "PROGRAMS": ["CIP42BACHL", "CIP09BACHL", "CIP03BACHL", "CIP44BACHL", "CIP31BACHL", "CIP23BACHL", "CIP40BACHL", "CIP22BACHL", "CIP43BACHL", "CIP27BACHL", "CIP16BACHL", "CIP11BACHL", "CIP50BACHL", "CIP38BACHL", "CIP13BACHL", "CIP45BACHL", "CIP14BACHL", "CIP26CERT1", "CIP26BACHL", "CIP54BACHL", "CIP52BACHL", "CIP05BACHL"], "SAT_AVG": "1055", "LONGITUDE": "-71.038653", "INSTNM": "University of Massachusetts-Boston", "LATITUDE": "42.314541", "CCSIZSET": "15", "INSTURL": "www.umb.edu"}, {"CITY": "Wellesley Hills", "STABBR": "MA", "ADM_RATE": "NULL", "ZIP": "02481-5399", "HIGHDEG": "2", "LOCALE": "21", "PROGRAMS": ["CIP13ASSOC", "CIP30ASSOC", "CIP24CERT1", "CIP11ASSOC", "CIP51ASSOC", "CIP13CERT1", "CIP51CERT2", "CIP51CERT1", "CIP50CERT1", "CIP43ASSOC", "CIP22CERT1", "CIP15ASSOC", "CIP27ASSOC", "CIP47CERT1", "CIP47CERT2", "CIP09CERT1", "CIP26ASSOC", "CIP44CERT1", "CIP41ASSOC", "CIP47ASSOC", "CIP19CERT1", "CIP44ASSOC"], "SAT_AVG": "NULL", "LONGITUDE": "-71.264004", "INSTNM": "Massachusetts Bay Community College", "LATITUDE": "42.312697", "CCSIZSET": "3", "INSTURL": "www.massbay.edu"}, {"CITY": "Boston", "STABBR": "MA", "ADM_RATE": "0.8656", "ZIP": "02115-5896", "HIGHDEG": "4", "LOCALE": "11", "PROGRAMS": ["CIP42BACHL", "CIP40BACHL", "CIP26BACHL"], "SAT_AVG": "1070", "LONGITUDE": "-71.100964", "INSTNM": "MCPHS University", "LATITUDE": "42.337036", "CCSIZSET": "13", "INSTURL": "www.mcphs.edu"}, {"CITY": "Boston", "STABBR": "MA", "ADM_RATE": "0.7133", "ZIP": "02115-5882", "HIGHDEG": "4", "LOCALE": "11", "PROGRAMS": ["CIP50CERT1", "CIP50CERT2", "CIP50BACHL", "CIP13BACHL", "CIP04BACHL"], "SAT_AVG": "1086", "LONGITUDE": "-71.099537", "INSTNM": "Massachusetts College of Art and Design", "LATITUDE": "42.33693", "CCSIZSET": "10", "INSTURL": "www.massart.edu"}, {"CITY": "Cambridge", "STABBR": "MA", "ADM_RATE": "0.083", "ZIP": "02139-4307", "HIGHDEG": "4", "LOCALE": "12", "PROGRAMS": ["CIP09BACHL", "CIP23BACHL", "CIP40BACHL", "CIP27BACHL", "CIP16BACHL", "CIP11BACHL", "CIP50BACHL", "CIP38BACHL", "CIP45BACHL", "CIP14BACHL", "CIP24BACHL", "CIP04BACHL", "CIP26BACHL", "CIP54BACHL", "CIP52BACHL", "CIP30BACHL"], "SAT_AVG": "1507", "LONGITUDE": "-71.092115", "INSTNM": "Massachusetts Institute of Technology", "LATITUDE": "42.360095", "CCSIZSET": "17", "INSTURL": "web.mit.edu/student/"}, {"CITY": "Buzzards Bay", "STABBR": "MA", "ADM_RATE": "0.7394", "ZIP": "02532-1803", "HIGHDEG": "4", "LOCALE": "22", "PROGRAMS": ["CIP03BACHL", "CIP43BACHL", "CIP14BACHL", "CIP49BACHL", "CIP52BACHL"], "SAT_AVG": "1065", "LONGITUDE": "-70.623953", "INSTNM": "Massachusetts Maritime Academy", "LATITUDE": "41.740538", "CCSIZSET": "11", "INSTURL": "www.maritime.edu"}, {"CITY": "Worcester", "STABBR": "MA", "ADM_RATE": "NULL", "ZIP": "01655", "HIGHDEG": "4", "LOCALE": "12", "PROGRAMS": [], "SAT_AVG": "NULL", "LONGITUDE": "-71.760689", "INSTNM": "University of Massachusetts Medical School Worcester", "LATITUDE": "42.277589", "CCSIZSET": "18", "INSTURL": "www.umassmed.edu"}, {"CITY": "Newton", "STABBR": "MA", "ADM_RATE": "NULL", "ZIP": "02459", "HIGHDEG": "4", "LOCALE": "13", "PROGRAMS": [], "SAT_AVG": "NULL", "LONGITUDE": "-71.203361", "INSTNM": "William James College", "LATITUDE": "42.295007", "CCSIZSET": "18", "INSTURL": "www.williamjames.edu"}, {"CITY": "Quincy", "STABBR": "MA", "ADM_RATE": "NULL", "ZIP": "02169", "HIGHDEG": "1", "LOCALE": "21", "PROGRAMS": ["CIP12CERT2", "CIP12CERT1"], "SAT_AVG": "NULL", "LONGITUDE": "-71.000967", "INSTNM": "Massachusetts School of Barbering", "LATITUDE": "42.247023", "CCSIZSET": "-2", "INSTURL": "massschoolofbarbering.com"}, {"CITY": "Brockton", "STABBR": "MA", "ADM_RATE": "NULL", "ZIP": "02302-3996", "HIGHDEG": "2", "LOCALE": "21", "PROGRAMS": ["CIP13ASSOC", "CIP30ASSOC", "CIP30CERT1", "CIP11CERT1", "CIP11ASSOC", "CIP51ASSOC", "CIP10CERT1", "CIP51CERT2", "CIP43ASSOC", "CIP15ASSOC", "CIP52ASSOC", "CIP24ASSOC", "CIP43CERT1", "CIP19ASSOC", "CIP50ASSOC", "CIP47CERT1", "CIP26CERT1", "CIP09ASSOC", "CIP12CERT1", "CIP52CERT2", "CIP52CERT1", "CIP12ASSOC", "CIP47ASSOC", "CIP19CERT1", "CIP44ASSOC"], "SAT_AVG": "NULL", "LONGITUDE": "-70.988944", "INSTNM": "Massasoit Community College", "LATITUDE": "42.076048", "CCSIZSET": "3", "INSTURL": "www.massasoit.mass.edu"}, {"CITY": "North Andover", "STABBR": "MA", "ADM_RATE": "0.7897", "ZIP": "01845", "HIGHDEG": "4", "LOCALE": "21", "PROGRAMS": ["CIP42BACHL", "CIP09BACHL", "CIP03BACHL", "CIP31BACHL", "CIP23BACHL", "CIP40BACHL", "CIP43BACHL", "CIP19BACHL", "CIP27BACHL", "CIP16BACHL", "CIP11BACHL", "CIP50BACHL", "CIP38BACHL", "CIP13BACHL", "CIP45BACHL", "CIP14BACHL", "CIP24BACHL", "CIP51BACHL", "CIP26BACHL", "CIP54BACHL", "CIP52BACHL", "CIP05BACHL", "CIP30BACHL"], "SAT_AVG": "NULL", "LONGITUDE": "-71.124216", "INSTNM": "Merrimack College", "LATITUDE": "42.668352", "CCSIZSET": "14", "INSTURL": "www.merrimack.edu"}, {"CITY": "Boston", "STABBR": "MA", "ADM_RATE": "NULL", "ZIP": "02129-4557", "HIGHDEG": "4", "LOCALE": "11", "PROGRAMS": ["CIP51BACHL"], "SAT_AVG": "NULL", "LONGITUDE": "-71.056518", "INSTNM": "MGH Institute of Health Professions", "LATITUDE": "42.373635", "CCSIZSET": "6", "INSTURL": "www.mghihp.edu"}, {"CITY": "Bedford", "STABBR": "MA", "ADM_RATE": "NULL", "ZIP": "01730-9124", "HIGHDEG": "2", "LOCALE": "21", "PROGRAMS": ["CIP13ASSOC", "CIP11CERT1", "CIP15CERT1", "CIP11ASSOC", "CIP51ASSOC", "CIP13CERT1", "CIP51CERT2", "CIP51CERT1", "CIP50CERT1", "CIP50CERT2", "CIP40ASSOC", "CIP22CERT1", "CIP31CERT1", "CIP15ASSOC", "CIP41CERT1", "CIP43CERT1", "CIP50ASSOC", "CIP22ASSOC", "CIP26ASSOC", "CIP22CERT2", "CIP41ASSOC", "CIP47ASSOC", "CIP45ASSOC"], "SAT_AVG": "NULL", "LONGITUDE": "-71.273966", "INSTNM": "Middlesex Community College", "LATITUDE": "42.525056", "CCSIZSET": "4", "INSTURL": "www.middlesex.mass.edu"}, {"CITY": "Beverly", "STABBR": "MA", "ADM_RATE": "NULL", "ZIP": "01915-4508", "HIGHDEG": "3", "LOCALE": "21", "PROGRAMS": ["CIP50CERT4", "CIP30CERT4", "CIP10BACHL", "CIP13CERT1", "CIP10CERT4", "CIP50BACHL", "CIP13BACHL", "CIP30BACHL"], "SAT_AVG": "NULL", "LONGITUDE": "-70.876419", "INSTNM": "Montserrat College of Art", "LATITUDE": "42.550416", "CCSIZSET": "8", "INSTURL": "www.montserrat.edu/"}, {"CITY": "South Hadley", "STABBR": "MA", "ADM_RATE": "0.5008", "ZIP": "01075-1489", "HIGHDEG": "4", "LOCALE": "21", "PROGRAMS": ["CIP42BACHL", "CIP03BACHL", "CIP23BACHL", "CIP40BACHL", "CIP27BACHL", "CIP16BACHL", "CIP11BACHL", "CIP50BACHL", "CIP38BACHL", "CIP13BACHL", "CIP45BACHL", "CIP04BACHL", "CIP26BACHL", "CIP54BACHL", "CIP05BACHL", "CIP30BACHL"], "SAT_AVG": "NULL", "LONGITUDE": "-72.573625", "INSTNM": "Mount Holyoke College", "LATITUDE": "42.257588", "CCSIZSET": "11", "INSTURL": "www.mtholyoke.edu"}, {"CITY": "Newton", "STABBR": "MA", "ADM_RATE": "0.6326", "ZIP": "02459", "HIGHDEG": "4", "LOCALE": "13", "PROGRAMS": ["CIP42BACHL", "CIP44BACHL", "CIP23BACHL", "CIP10BACHL", "CIP51ASSOC", "CIP43BACHL", "CIP24ASSOC", "CIP50BACHL", "CIP13BACHL", "CIP24BACHL", "CIP01BACHL", "CIP51BACHL", "CIP26BACHL", "CIP52BACHL", "CIP12BACHL", "CIP12ASSOC", "CIP05BACHL"], "SAT_AVG": "906", "LONGITUDE": "-71.194658", "INSTNM": "Mount Ida College", "LATITUDE": "42.293205", "CCSIZSET": "11", "INSTURL": "www.mountida.edu"}, {"CITY": "Gardner", "STABBR": "MA", "ADM_RATE": "NULL", "ZIP": "01440-1000", "HIGHDEG": "2", "LOCALE": "41", "PROGRAMS": ["CIP15CERT1", "CIP11ASSOC", "CIP51ASSOC", "CIP51CERT2", "CIP51CERT1", "CIP50CERT1", "CIP43ASSOC", "CIP31CERT1", "CIP15ASSOC", "CIP43CERT1", "CIP19ASSOC", "CIP50ASSOC", "CIP47CERT2", "CIP26CERT1", "CIP26ASSOC", "CIP03ASSOC", "CIP44CERT1", "CIP47ASSOC", "CIP10ASSOC", "CIP44ASSOC"], "SAT_AVG": "NULL", "LONGITUDE": "-71.984149", "INSTNM": "Mount Wachusett Community College", "LATITUDE": "42.593151", "CCSIZSET": "3", "INSTURL": "MWCC.EDU"}, {"CITY": "Watertown", "STABBR": "MA", "ADM_RATE": "NULL", "ZIP": "02472", "HIGHDEG": "1", "LOCALE": "21", "PROGRAMS": ["CIP51CERT1"], "SAT_AVG": "NULL", "LONGITUDE": "-71.190748", "INSTNM": "Cortiva Institute-Boston", "LATITUDE": "42.361656", "CCSIZSET": "-2", "INSTURL": "www.cortiva.com"}, {"CITY": "Boston", "STABBR": "MA", "ADM_RATE": "0.9213", "ZIP": "02115-5596", "HIGHDEG": "4", "LOCALE": "11", "PROGRAMS": ["CIP50CERT4", "CIP50CERT1", "CIP50BACHL"], "SAT_AVG": "NULL", "LONGITUDE": "-71.096941", "INSTNM": "School of the Museum of Fine Arts at Tufts University", "LATITUDE": "42.338958", "CCSIZSET": "6", "INSTURL": "www.smfa.edu/"}, {"CITY": "New Bedford", "STABBR": "MA", "ADM_RATE": "NULL", "ZIP": "02720-3445", "HIGHDEG": "1", "LOCALE": "22", "PROGRAMS": ["CIP12CERT2"], "SAT_AVG": "NULL", "LONGITUDE": "-70.925187", "INSTNM": "Rob Roy Academy-New Bedford", "LATITUDE": "41.671921", "CCSIZSET": "-2", "INSTURL": "www.rob-roy.com"}, {"CITY": "Boston", "STABBR": "MA", "ADM_RATE": "0.3239", "ZIP": "02115-5018", "HIGHDEG": "4", "LOCALE": "11", "PROGRAMS": ["CIP50CERT4", "CIP50BACHL"], "SAT_AVG": "NULL", "LONGITUDE": "-71.086321", "INSTNM": "The New England Conservatory of Music", "LATITUDE": "42.340998", "CCSIZSET": "7", "INSTURL": "necmusic.edu"}, {"CITY": "Boston", "STABBR": "MA", "ADM_RATE": "NULL", "ZIP": "02115", "HIGHDEG": "4", "LOCALE": "11", "PROGRAMS": ["CIP51BACHL"], "SAT_AVG": "NULL", "LONGITUDE": "-71.086521", "INSTNM": "New England College of Optometry", "LATITUDE": "42.351656", "CCSIZSET": "18", "INSTURL": "www.neco.edu"}, {"CITY": "Newton", "STABBR": "MA", "ADM_RATE": "NULL", "ZIP": "02458", "HIGHDEG": "4", "LOCALE": "13", "PROGRAMS": [], "SAT_AVG": "NULL", "LONGITUDE": "-71.19491", "INSTNM": "New England School of Acupuncture", "LATITUDE": "42.363713", "CCSIZSET": "18", "INSTURL": "www.nesa.edu"}, {"CITY": "Boston", "STABBR": "MA", "ADM_RATE": "NULL", "ZIP": "02116", "HIGHDEG": "4", "LOCALE": "11", "PROGRAMS": [], "SAT_AVG": "NULL", "LONGITUDE": "-71.0665", "INSTNM": "New England Law-Boston", "LATITUDE": "42.350833", "CCSIZSET": "18", "INSTURL": "www.nesl.edu"}, {"CITY": "Boston", "STABBR": "MA", "ADM_RATE": "0.5211", "ZIP": "02215", "HIGHDEG": "1", "LOCALE": "11", "PROGRAMS": ["CIP50CERT4"], "SAT_AVG": "NULL", "LONGITUDE": "-71.097005", "INSTNM": "New England School of Photography", "LATITUDE": "42.349179", "CCSIZSET": "-2", "INSTURL": "https://www.NESOP.edu"}, {"CITY": "Brookline", "STABBR": "MA", "ADM_RATE": "0.7914", "ZIP": "02445", "HIGHDEG": "3", "LOCALE": "21", "PROGRAMS": ["CIP42BACHL", "CIP09BACHL", "CIP31BACHL", "CIP22BACHL", "CIP43BACHL", "CIP52ASSOC", "CIP24ASSOC", "CIP11BACHL", "CIP50BACHL", "CIP12CERT1", "CIP51BACHL", "CIP52BACHL", "CIP12BACHL", "CIP12ASSOC", "CIP30BACHL"], "SAT_AVG": "NULL", "LONGITUDE": "-71.142082", "INSTNM": "Newbury College", "LATITUDE": "42.331032", "CCSIZSET": "7", "INSTURL": "www.newbury.edu"}, {"CITY": "Dudley", "STABBR": "MA", "ADM_RATE": "0.8268", "ZIP": "01571-5000", "HIGHDEG": "4", "LOCALE": "21", "PROGRAMS": ["CIP42BACHL", "CIP31BACHL", "CIP23BACHL", "CIP43BACHL", "CIP27BACHL", "CIP13BACHL", "CIP54BACHL"], "SAT_AVG": "NULL", "LONGITUDE": "-71.929644", "INSTNM": "Nichols College", "LATITUDE": "42.042462", "CCSIZSET": "11", "INSTURL": "www.nichols.edu"}, {"CITY": "North Adams", "STABBR": "MA", "ADM_RATE": "0.7341", "ZIP": "01247-4100", "HIGHDEG": "4", "LOCALE": "31", "PROGRAMS": ["CIP42BACHL", "CIP03BACHL", "CIP23BACHL", "CIP40BACHL", "CIP27BACHL", "CIP11BACHL", "CIP50BACHL", "CIP38BACHL", "CIP13BACHL", "CIP45BACHL", "CIP51BACHL", "CIP26BACHL", "CIP54BACHL", "CIP52BACHL", "CIP52CERT1", "CIP30BACHL"], "SAT_AVG": "1016", "LONGITUDE": "-73.1035", "INSTNM": "Massachusetts College of Liberal Arts", "LATITUDE": "42.692427", "CCSIZSET": "11", "INSTURL": "www.mcla.edu"}, {"CITY": "Boston", "STABBR": "MA", "ADM_RATE": "NULL", "ZIP": "02109", "HIGHDEG": "1", "LOCALE": "11", "PROGRAMS": ["CIP47CERT4", "CIP46CERT2", "CIP46CERT4", "CIP47CERT2", "CIP48CERT4"], "SAT_AVG": "NULL", "LONGITUDE": "-71.054671", "INSTNM": "North Bennet Street School", "LATITUDE": "42.36268", "CCSIZSET": "-2", "INSTURL": "www.nbss.edu"}, {"CITY": "Danvers", "STABBR": "MA", "ADM_RATE": "NULL", "ZIP": "01923-0840", "HIGHDEG": "2", "LOCALE": "21", "PROGRAMS": ["CIP13ASSOC", "CIP14ASSOC", "CIP15CERT1", "CIP11ASSOC", "CIP51ASSOC", "CIP13CERT1", "CIP51CERT2", "CIP51CERT1", "CIP50CERT1", "CIP46ASSOC", "CIP22CERT1", "CIP15ASSOC", "CIP52ASSOC", "CIP41CERT1", "CIP24ASSOC", "CIP43CERT1", "CIP19ASSOC", "CIP50ASSOC", "CIP22ASSOC", "CIP46CERT1", "CIP12CERT1", "CIP03ASSOC", "CIP01ASSOC", "CIP44CERT1", "CIP41ASSOC", "CIP52CERT1", "CIP12ASSOC", "CIP19CERT1", "CIP01CERT2", "CIP49ASSOC"], "SAT_AVG": "NULL", "LONGITUDE": "-70.968337", "INSTNM": "North Shore Community College", "LATITUDE": "42.597283", "CCSIZSET": "3", "INSTURL": "www.northshore.edu"}, {"CITY": "Brookline", "STABBR": "MA", "ADM_RATE": "NULL", "ZIP": "02445-7295", "HIGHDEG": "3", "LOCALE": "21", "PROGRAMS": ["CIP10BACHL", "CIP11BACHL", "CIP50ASSOC", "CIP50BACHL", "CIP52BACHL", "CIP10ASSOC"], "SAT_AVG": "NULL", "LONGITUDE": "-71.115654", "INSTNM": "The New England Institute of Art", "LATITUDE": "42.332079", "CCSIZSET": "6", "INSTURL": "www.artinstitutes.edu/boston"}, {"CITY": "Boston", "STABBR": "MA", "ADM_RATE": "0.2848", "ZIP": "02115-5005", "HIGHDEG": "4", "LOCALE": "11", "PROGRAMS": ["CIP42BACHL", "CIP09BACHL", "CIP03BACHL", "CIP44BACHL", "CIP23BACHL", "CIP10BACHL", "CIP40BACHL", "CIP43BACHL", "CIP27BACHL", "CIP16BACHL", "CIP11BACHL", "CIP50BACHL", "CIP38BACHL", "CIP45BACHL", "CIP14BACHL", "CIP24BACHL", "CIP04BACHL", "CIP51BACHL", "CIP26BACHL", "CIP54BACHL", "CIP52BACHL", "CIP05BACHL", "CIP15BACHL"], "SAT_AVG": "1435", "LONGITUDE": "-71.088782", "INSTNM": "Northeastern University", "LATITUDE": "42.339992", "CCSIZSET": "16", "INSTURL": "www.northeastern.edu"}, {"CITY": "Haverhill", "STABBR": "MA", "ADM_RATE": "NULL", "ZIP": "01830-2399", "HIGHDEG": "2", "LOCALE": "21", "PROGRAMS": ["CIP13ASSOC", "CIP30ASSOC", "CIP15CERT2", "CIP15CERT1", "CIP11ASSOC", "CIP51ASSOC", "CIP13CERT1", "CIP10CERT1", "CIP51CERT2", "CIP51CERT1", "CIP50CERT1", "CIP50CERT2", "CIP31ASSOC", "CIP43ASSOC", "CIP15ASSOC", "CIP43CERT1", "CIP50ASSOC", "CIP22ASSOC", "CIP16ASSOC", "CIP16CERT2", "CIP16CERT1", "CIP22CERT2", "CIP41ASSOC", "CIP52CERT1", "CIP10ASSOC", "CIP44ASSOC"], "SAT_AVG": "NULL", "LONGITUDE": "-71.047475", "INSTNM": "Northern Essex Community College", "LATITUDE": "42.796148", "CCSIZSET": "3", "INSTURL": "www.necc.mass.edu/"}, {"CITY": "Chicopee", "STABBR": "MA", "ADM_RATE": "0.7488", "ZIP": "01013", "HIGHDEG": "4", "LOCALE": "21", "PROGRAMS": ["CIP42BACHL", "CIP44BACHL", "CIP23BACHL", "CIP51ASSOC", "CIP40BACHL", "CIP22BACHL", "CIP43BACHL", "CIP27BACHL", "CIP16BACHL", "CIP11BACHL", "CIP22ASSOC", "CIP50BACHL", "CIP38BACHL", "CIP13BACHL", "CIP45BACHL", "CIP24BACHL", "CIP26BACHL", "CIP54BACHL", "CIP22CERT2", "CIP52BACHL", "CIP30BACHL", "CIP39BACHL"], "SAT_AVG": "976", "LONGITUDE": "-72.601541", "INSTNM": "College of Our Lady of the Elms", "LATITUDE": "42.14179", "CCSIZSET": "10", "INSTURL": "www.elms.edu"}, {"CITY": "Chestnut Hill", "STABBR": "MA", "ADM_RATE": "0.7094", "ZIP": "02467", "HIGHDEG": "4", "LOCALE": "21", "PROGRAMS": ["CIP42BACHL", "CIP09BACHL", "CIP23BACHL", "CIP51ASSOC", "CIP52ASSOC", "CIP24ASSOC", "CIP19ASSOC", "CIP50ASSOC", "CIP50BACHL", "CIP13BACHL", "CIP45BACHL", "CIP24BACHL", "CIP26ASSOC", "CIP09ASSOC", "CIP51BACHL", "CIP26BACHL", "CIP54BACHL", "CIP52BACHL"], "SAT_AVG": "775", "LONGITUDE": "-71.156973", "INSTNM": "Pine Manor College", "LATITUDE": "42.319568", "CCSIZSET": "8", "INSTURL": "www.pmc.edu"}, {"CITY": "Weston", "STABBR": "MA", "ADM_RATE": "NULL", "ZIP": "02493-2699", "HIGHDEG": "4", "LOCALE": "21", "PROGRAMS": [], "SAT_AVG": "NULL", "LONGITUDE": "-71.2717", "INSTNM": "Pope St John XXIII National Seminary", "LATITUDE": "42.3455", "CCSIZSET": "18", "INSTURL": "www.psjs.edu"}, {"CITY": "Quincy", "STABBR": "MA", "ADM_RATE": "NULL", "ZIP": "02169", "HIGHDEG": "2", "LOCALE": "21", "PROGRAMS": ["CIP13ASSOC", "CIP30CERT1", "CIP11CERT2", "CIP11ASSOC", "CIP51ASSOC", "CIP13CERT2", "CIP51CERT2", "CIP51CERT1", "CIP50CERT1", "CIP43ASSOC", "CIP52ASSOC", "CIP41CERT1", "CIP24ASSOC", "CIP43CERT1", "CIP50ASSOC", "CIP22ASSOC", "CIP26CERT1", "CIP26ASSOC", "CIP22CERT2", "CIP44CERT2", "CIP41ASSOC", "CIP52CERT1", "CIP44ASSOC"], "SAT_AVG": "NULL", "LONGITUDE": "-71.003091", "INSTNM": "Quincy College", "LATITUDE": "42.25194", "CCSIZSET": "3", "INSTURL": "www.quincycollege.edu"}, {"CITY": "Worcester", "STABBR": "MA", "ADM_RATE": "NULL", "ZIP": "01606-2092", "HIGHDEG": "2", "LOCALE": "12", "PROGRAMS": ["CIP13ASSOC", "CIP14ASSOC", "CIP15CERT1", "CIP11ASSOC", "CIP51ASSOC", "CIP13CERT1", "CIP51CERT2", "CIP51CERT1", "CIP43ASSOC", "CIP15ASSOC", "CIP43CERT1", "CIP47CERT1", "CIP05ASSOC", "CIP26ASSOC", "CIP44CERT1", "CIP44CERT2", "CIP47ASSOC", "CIP44ASSOC"], "SAT_AVG": "NULL", "LONGITUDE": "-71.793568", "INSTNM": "Quinsigamond Community College", "LATITUDE": "42.314675", "CCSIZSET": "4", "INSTURL": "www.qcc.edu"}, {"CITY": "Weston", "STABBR": "MA", "ADM_RATE": "0.8423", "ZIP": "02493-1571", "HIGHDEG": "4", "LOCALE": "21", "PROGRAMS": ["CIP42BACHL", "CIP09BACHL", "CIP44BACHL", "CIP31BACHL", "CIP23BACHL", "CIP51ASSOC", "CIP40BACHL", "CIP16BACHL", "CIP11BACHL", "CIP50BACHL", "CIP13BACHL", "CIP45BACHL", "CIP24BACHL", "CIP51BACHL", "CIP26BACHL", "CIP54BACHL", "CIP52BACHL", "CIP30BACHL"], "SAT_AVG": "NULL", "LONGITUDE": "-71.309126", "INSTNM": "Regis College", "LATITUDE": "42.351105", "CCSIZSET": "10", "INSTURL": "www.regiscollege.edu"}, {"CITY": "Roxbury Crossing", "STABBR": "MA", "ADM_RATE": "NULL", "ZIP": "02120-3400", "HIGHDEG": "2", "LOCALE": "11", "PROGRAMS": ["CIP13ASSOC", "CIP24CERT1", "CIP14ASSOC", "CIP11CERT2", "CIP15CERT1", "CIP11ASSOC", "CIP51ASSOC", "CIP10CERT1", "CIP51CERT2", "CIP51CERT1", "CIP40ASSOC", "CIP43ASSOC", "CIP52ASSOC", "CIP24ASSOC", "CIP43CERT1", "CIP27ASSOC", "CIP26CERT1", "CIP26CERT2", "CIP26ASSOC", "CIP52CERT2", "CIP52CERT1"], "SAT_AVG": "NULL", "LONGITUDE": "-71.095428", "INSTNM": "Roxbury Community College", "LATITUDE": "42.329723", "CCSIZSET": "2", "INSTURL": "www.rcc.mass.edu"}, {"CITY": "Brighton", "STABBR": "MA", "ADM_RATE": "NULL", "ZIP": "02135-3846", "HIGHDEG": "4", "LOCALE": "11", "PROGRAMS": ["CIP39BACHL"], "SAT_AVG": "NULL", "LONGITUDE": "-71.161998", "INSTNM": "Saint John's Seminary", "LATITUDE": "42.344146", "CCSIZSET": "8", "INSTURL": "www.sjs.edu"}, {"CITY": "Salem", "STABBR": "MA", "ADM_RATE": "0.749", "ZIP": "01970", "HIGHDEG": "4", "LOCALE": "21", "PROGRAMS": ["CIP42BACHL", "CIP09BACHL", "CIP44BACHL", "CIP31BACHL", "CIP23BACHL", "CIP40BACHL", "CIP27BACHL", "CIP16BACHL", "CIP11BACHL", "CIP50BACHL", "CIP38BACHL", "CIP13BACHL", "CIP45BACHL", "CIP24BACHL", "CIP01BACHL", "CIP51BACHL", "CIP26BACHL", "CIP49BACHL", "CIP54BACHL", "CIP52BACHL"], "SAT_AVG": "NULL", "LONGITUDE": "-70.889321", "INSTNM": "Salem State University", "LATITUDE": "42.502879", "CCSIZSET": "13", "INSTURL": "www.salemstate.edu"}, {"CITY": "West Boylston", "STABBR": "MA", "ADM_RATE": "NULL", "ZIP": "01583", "HIGHDEG": "2", "LOCALE": "21", "PROGRAMS": ["CIP51ASSOC", "CIP51CERT2", "CIP51CERT1", "CIP52ASSOC", "CIP12CERT2"], "SAT_AVG": "NULL", "LONGITUDE": "-71.787915", "INSTNM": "Salter College-West Boylston", "LATITUDE": "42.350662", "CCSIZSET": "1", "INSTURL": "www.salter.edu"}, {"CITY": "Boston", "STABBR": "MA", "ADM_RATE": "0.5757", "ZIP": "02115-5898", "HIGHDEG": "4", "LOCALE": "11", "PROGRAMS": ["CIP42BACHL", "CIP09BACHL", "CIP03BACHL", "CIP44BACHL", "CIP31BACHL", "CIP23BACHL", "CIP40BACHL", "CIP19BACHL", "CIP27BACHL", "CIP16BACHL", "CIP11BACHL", "CIP50BACHL", "CIP38BACHL", "CIP13BACHL", "CIP45BACHL", "CIP01BACHL", "CIP51BACHL", "CIP26BACHL", "CIP54BACHL", "CIP52BACHL", "CIP05BACHL", "CIP30BACHL"], "SAT_AVG": "1163", "LONGITUDE": "-71.099967", "INSTNM": "Simmons College", "LATITUDE": "42.3393", "CCSIZSET": "14", "INSTURL": "www.simmons.edu"}, {"CITY": "Great Barrington", "STABBR": "MA", "ADM_RATE": "0.8945", "ZIP": "01230-9702", "HIGHDEG": "3", "LOCALE": "41", "PROGRAMS": ["CIP42BACHL", "CIP03BACHL", "CIP23BACHL", "CIP40BACHL", "CIP27BACHL", "CIP24ASSOC", "CIP16BACHL", "CIP11BACHL", "CIP50BACHL", "CIP38BACHL", "CIP45BACHL", "CIP14BACHL", "CIP24BACHL", "CIP51BACHL", "CIP26BACHL", "CIP54BACHL", "CIP05BACHL", "CIP30BACHL"], "SAT_AVG": "NULL", "LONGITUDE": "-73.380008", "INSTNM": "Bard College at Simon's Rock", "LATITUDE": "42.209241", "CCSIZSET": "8", "INSTURL": "www.simons-rock.edu/"}, {"CITY": "Northampton", "STABBR": "MA", "ADM_RATE": "0.3789", "ZIP": "01063", "HIGHDEG": "4", "LOCALE": "21", "PROGRAMS": ["CIP42BACHL", "CIP03BACHL", "CIP31BACHL", "CIP23BACHL", "CIP40BACHL", "CIP27BACHL", "CIP16BACHL", "CIP11BACHL", "CIP50BACHL", "CIP38BACHL", "CIP13BACHL", "CIP45BACHL", "CIP14BACHL", "CIP24BACHL", "CIP04BACHL", "CIP51BACHL", "CIP26BACHL", "CIP54BACHL", "CIP05BACHL", "CIP30BACHL"], "SAT_AVG": "NULL", "LONGITUDE": "-72.638094", "INSTNM": "Smith College", "LATITUDE": "42.317933", "CCSIZSET": "11", "INSTURL": "www.smith.edu"}, {"CITY": "South Easton", "STABBR": "MA", "ADM_RATE": "0.75", "ZIP": "02375", "HIGHDEG": "1", "LOCALE": "21", "PROGRAMS": ["CIP51CERT2", "CIP51CERT1", "CIP47CERT1", "CIP12CERT1"], "SAT_AVG": "NULL", "LONGITUDE": "-71.081263", "INSTNM": "Southeastern Technical Institute", "LATITUDE": "42.011288", "CCSIZSET": "-2", "INSTURL": "www.stitech.edu"}, {"CITY": "Springfield", "STABBR": "MA", "ADM_RATE": "0.6415", "ZIP": "01109-3797", "HIGHDEG": "4", "LOCALE": "12", "PROGRAMS": ["CIP42BACHL", "CIP09BACHL", "CIP31BACHL", "CIP23BACHL", "CIP43BACHL", "CIP27BACHL", "CIP11BACHL", "CIP50BACHL", "CIP13BACHL", "CIP45BACHL", "CIP24BACHL", "CIP51BACHL", "CIP26BACHL", "CIP54BACHL", "CIP52BACHL", "CIP05BACHL", "CIP30BACHL"], "SAT_AVG": "1042", "LONGITUDE": "-72.555688", "INSTNM": "Springfield College", "LATITUDE": "42.105033", "CCSIZSET": "14", "INSTURL": "www.springfield.edu/"}, {"CITY": "Springfield", "STABBR": "MA", "ADM_RATE": "NULL", "ZIP": "01105-1296", "HIGHDEG": "2", "LOCALE": "12", "PROGRAMS": ["CIP13ASSOC", "CIP14ASSOC", "CIP11CERT1", "CIP15CERT1", "CIP11ASSOC", "CIP51ASSOC", "CIP10CERT1", "CIP51CERT2", "CIP51CERT1", "CIP50CERT1", "CIP46ASSOC", "CIP40ASSOC", "CIP31ASSOC", "CIP43ASSOC", "CIP15ASSOC", "CIP52ASSOC", "CIP24ASSOC", "CIP43CERT1", "CIP27ASSOC", "CIP50ASSOC", "CIP46CERT1", "CIP47CERT1", "CIP26CERT1", "CIP26ASSOC", "CIP12CERT2", "CIP01ASSOC", "CIP04ASSOC", "CIP01CERT1", "CIP52CERT2", "CIP47ASSOC", "CIP10ASSOC", "CIP48CERT1"], "SAT_AVG": "NULL", "LONGITUDE": "-72.581598", "INSTNM": "Springfield Technical Community College", "LATITUDE": "42.108393", "CCSIZSET": "3", "INSTURL": "www.stcc.edu"}, {"CITY": "North Dartmouth", "STABBR": "MA", "ADM_RATE": "0.7626", "ZIP": "02747-2300", "HIGHDEG": "4", "LOCALE": "22", "PROGRAMS": ["CIP42BACHL", "CIP23BACHL", "CIP40BACHL", "CIP51CERT1", "CIP50CERT1", "CIP27BACHL", "CIP16BACHL", "CIP11BACHL", "CIP50BACHL", "CIP38BACHL", "CIP13BACHL", "CIP14BACHL", "CIP26BACHL", "CIP54BACHL", "CIP52CERT2", "CIP52CERT1", "CIP30BACHL"], "SAT_AVG": "1025", "LONGITUDE": "-71.005528", "INSTNM": "University of Massachusetts-Dartmouth", "LATITUDE": "41.628861", "CCSIZSET": "14", "INSTURL": "www.umassd.edu"}, {"CITY": "Easton", "STABBR": "MA", "ADM_RATE": "0.7517", "ZIP": "02357-6110", "HIGHDEG": "3", "LOCALE": "21", "PROGRAMS": ["CIP42BACHL", "CIP09BACHL", "CIP03BACHL", "CIP44BACHL", "CIP23BACHL", "CIP40BACHL", "CIP27BACHL", "CIP16BACHL", "CIP11BACHL", "CIP50BACHL", "CIP38BACHL", "CIP13BACHL", "CIP45BACHL", "CIP51BACHL", "CIP26BACHL", "CIP54BACHL", "CIP52BACHL", "CIP05BACHL", "CIP30BACHL"], "SAT_AVG": "NULL", "LONGITUDE": "-71.078123", "INSTNM": "Stonehill College", "LATITUDE": "42.061448", "CCSIZSET": "11", "INSTURL": "www.stonehill.edu"}, {"CITY": "Boston", "STABBR": "MA", "ADM_RATE": "0.8237", "ZIP": "02108-2770", "HIGHDEG": "4", "LOCALE": "11", "PROGRAMS": ["CIP30ASSOC", "CIP42BACHL", "CIP09BACHL", "CIP03BACHL", "CIP50CERT4", "CIP44BACHL", "CIP15CERT2", "CIP23BACHL", "CIP10BACHL", "CIP13CERT2", "CIP40BACHL", "CIP51CERT4", "CIP51CERT2", "CIP50CERT2", "CIP22BACHL", "CIP43BACHL", "CIP27BACHL", "CIP52ASSOC", "CIP24ASSOC", "CIP16BACHL", "CIP11BACHL", "CIP50ASSOC", "CIP22ASSOC", "CIP50BACHL", "CIP23CERT4", "CIP38BACHL", "CIP13BACHL", "CIP45BACHL", "CIP14BACHL", "CIP24BACHL", "CIP51BACHL", "CIP26BACHL", "CIP54BACHL", "CIP22CERT2", "CIP52BACHL", "CIP44CERT2", "CIP52CERT2", "CIP52CERT1", "CIP52CERT4", "CIP45ASSOC", "CIP05BACHL", "CIP30BACHL", "CIP15BACHL"], "SAT_AVG": "1024", "LONGITUDE": "-71.06192", "INSTNM": "Suffolk University", "LATITUDE": "42.359134", "CCSIZSET": "12", "INSTURL": "www.suffolk.edu"}, {"CITY": "Taunton", "STABBR": "MA", "ADM_RATE": "NULL", "ZIP": "02780-5339", "HIGHDEG": "1", "LOCALE": "21", "PROGRAMS": ["CIP12CERT2", "CIP12CERT1"], "SAT_AVG": "NULL", "LONGITUDE": "-71.091871", "INSTNM": "Rob Roy Academy-Taunton", "LATITUDE": "41.901917", "CCSIZSET": "-2", "INSTURL": "www.rob-roy.com"}, {"CITY": "Medford", "STABBR": "MA", "ADM_RATE": "0.161", "ZIP": "02155-5555", "HIGHDEG": "4", "LOCALE": "21", "PROGRAMS": ["CIP42BACHL", "CIP03BACHL", "CIP23BACHL", "CIP40BACHL", "CIP19BACHL", "CIP27BACHL", "CIP16BACHL", "CIP11BACHL", "CIP50BACHL", "CIP38BACHL", "CIP45BACHL", "CIP14BACHL", "CIP04BACHL", "CIP51BACHL", "CIP26BACHL", "CIP54BACHL", "CIP05BACHL", "CIP30BACHL"], "SAT_AVG": "1424", "LONGITUDE": "-71.121689", "INSTNM": "Tufts University", "LATITUDE": "42.406994", "CCSIZSET": "17", "INSTURL": "www.tufts.edu"}, {"CITY": "Wellesley", "STABBR": "MA", "ADM_RATE": "0.2985", "ZIP": "02481-8203", "HIGHDEG": "3", "LOCALE": "21", "PROGRAMS": ["CIP42BACHL", "CIP03BACHL", "CIP23BACHL", "CIP40BACHL", "CIP27BACHL", "CIP16BACHL", "CIP11BACHL", "CIP50BACHL", "CIP38BACHL", "CIP45BACHL", "CIP04BACHL", "CIP26BACHL", "CIP54BACHL", "CIP05BACHL", "CIP30BACHL"], "SAT_AVG": "1369", "LONGITUDE": "-71.307966", "INSTNM": "Wellesley College", "LATITUDE": "42.293765", "CCSIZSET": "11", "INSTURL": "www.wellesley.edu"}, {"CITY": "Boston", "STABBR": "MA", "ADM_RATE": "0.6667", "ZIP": "02115", "HIGHDEG": "4", "LOCALE": "11", "PROGRAMS": ["CIP15CERT1", "CIP10CERT1", "CIP46ASSOC", "CIP15ASSOC", "CIP52ASSOC", "CIP11BACHL", "CIP50BACHL", "CIP14BACHL", "CIP04BACHL", "CIP52BACHL", "CIP15BACHL"], "SAT_AVG": "1104", "LONGITUDE": "-71.094983", "INSTNM": "Wentworth Institute of Technology", "LATITUDE": "42.336632", "CCSIZSET": "13", "INSTURL": "WWW.WIT.EDU"}, {"CITY": "Springfield", "STABBR": "MA", "ADM_RATE": "0.8094", "ZIP": "01119-2684", "HIGHDEG": "4", "LOCALE": "12", "PROGRAMS": ["CIP42BACHL", "CIP09BACHL", "CIP44BACHL", "CIP31BACHL", "CIP23BACHL", "CIP40BACHL", "CIP22BACHL", "CIP43BACHL", "CIP27BACHL", "CIP24ASSOC", "CIP11BACHL", "CIP50BACHL", "CIP38BACHL", "CIP13BACHL", "CIP45BACHL", "CIP14BACHL", "CIP24BACHL", "CIP51BACHL", "CIP26BACHL", "CIP54BACHL", "CIP05BACHL", "CIP30BACHL"], "SAT_AVG": "1080", "LONGITUDE": "-72.518789", "INSTNM": "Western New England University", "LATITUDE": "42.115837", "CCSIZSET": "14", "INSTURL": "www1.wne.edu"}, {"CITY": "Westfield", "STABBR": "MA", "ADM_RATE": "0.7961", "ZIP": "01086-1630", "HIGHDEG": "4", "LOCALE": "21", "PROGRAMS": ["CIP42BACHL", "CIP09BACHL", "CIP03BACHL", "CIP44BACHL", "CIP31BACHL", "CIP23BACHL", "CIP40BACHL", "CIP27BACHL", "CIP16BACHL", "CIP11BACHL", "CIP50BACHL", "CIP13BACHL", "CIP04BACHL", "CIP51BACHL", "CIP26BACHL", "CIP54BACHL", "CIP05BACHL"], "SAT_AVG": "1001", "LONGITUDE": "-72.795673", "INSTNM": "Westfield State University", "LATITUDE": "42.131589", "CCSIZSET": "14", "INSTURL": "www.westfield.ma.edu"}, {"CITY": "Norton", "STABBR": "MA", "ADM_RATE": "0.6455", "ZIP": "02766-2322", "HIGHDEG": "3", "LOCALE": "21", "PROGRAMS": ["CIP42BACHL", "CIP03BACHL", "CIP23BACHL", "CIP40BACHL", "CIP27BACHL", "CIP16BACHL", "CIP11BACHL", "CIP50BACHL", "CIP38BACHL", "CIP13BACHL", "CIP45BACHL", "CIP26BACHL", "CIP54BACHL", "CIP05BACHL", "CIP30BACHL"], "SAT_AVG": "NULL", "LONGITUDE": "-71.184167", "INSTNM": "Wheaton College", "LATITUDE": "41.966813", "CCSIZSET": "11", "INSTURL": "www.wheatoncollege.edu"}, {"CITY": "Boston", "STABBR": "MA", "ADM_RATE": "0.9542", "ZIP": "02215-4104", "HIGHDEG": "4", "LOCALE": "11", "PROGRAMS": ["CIP42BACHL", "CIP09BACHL", "CIP03BACHL", "CIP44BACHL", "CIP19BACHL", "CIP27BACHL", "CIP50BACHL", "CIP13BACHL", "CIP45BACHL", "CIP24BACHL", "CIP05BACHL"], "SAT_AVG": "944", "LONGITUDE": "-71.10582", "INSTNM": "Wheelock College", "LATITUDE": "42.342503", "CCSIZSET": "11", "INSTURL": "www.wheelock.edu"}, {"CITY": "Williamstown", "STABBR": "MA", "ADM_RATE": "0.1761", "ZIP": "01267", "HIGHDEG": "4", "LOCALE": "31", "PROGRAMS": ["CIP42BACHL", "CIP03BACHL", "CIP23BACHL", "CIP40BACHL", "CIP27BACHL", "CIP16BACHL", "CIP11BACHL", "CIP50BACHL", "CIP38BACHL", "CIP45BACHL", "CIP26BACHL", "CIP54BACHL", "CIP05BACHL", "CIP30BACHL"], "SAT_AVG": "1442", "LONGITUDE": "-73.205888", "INSTNM": "Williams College", "LATITUDE": "42.711669", "CCSIZSET": "11", "INSTURL": "www.williams.edu"}, {"CITY": "Worcester", "STABBR": "MA", "ADM_RATE": "0.4855", "ZIP": "01609-2280", "HIGHDEG": "4", "LOCALE": "12", "PROGRAMS": ["CIP42BACHL", "CIP09BACHL", "CIP40BACHL", "CIP27BACHL", "CIP11BACHL", "CIP45BACHL", "CIP14BACHL", "CIP24BACHL", "CIP26BACHL", "CIP52BACHL", "CIP30BACHL"], "SAT_AVG": "NULL", "LONGITUDE": "-71.808792", "INSTNM": "Worcester Polytechnic Institute", "LATITUDE": "42.275067", "CCSIZSET": "14", "INSTURL": "www.wpi.edu"}, {"CITY": "Worcester", "STABBR": "MA", "ADM_RATE": "0.6857", "ZIP": "01602-2597", "HIGHDEG": "4", "LOCALE": "12", "PROGRAMS": ["CIP42BACHL", "CIP09BACHL", "CIP23BACHL", "CIP40BACHL", "CIP43BACHL", "CIP27BACHL", "CIP16BACHL", "CIP11BACHL", "CIP50BACHL", "CIP13BACHL", "CIP45BACHL", "CIP51BACHL", "CIP26BACHL", "CIP54BACHL", "CIP52BACHL"], "SAT_AVG": "1020", "LONGITUDE": "-71.844019", "INSTNM": "Worcester State University", "LATITUDE": "42.267534", "CCSIZSET": "13", "INSTURL": "www.worcester.edu"}, {"CITY": "Haverhill", "STABBR": "MA", "ADM_RATE": "NULL", "ZIP": "01835", "HIGHDEG": "4", "LOCALE": "21", "PROGRAMS": [], "SAT_AVG": "NULL", "LONGITUDE": "-71.079336", "INSTNM": "Northpoint Bible College", "LATITUDE": "42.765366", "CCSIZSET": "8", "INSTURL": "www.northpoint.edu"}, {"CITY": "Canton", "STABBR": "MA", "ADM_RATE": "0.6364", "ZIP": "02021", "HIGHDEG": "1", "LOCALE": "21", "PROGRAMS": ["CIP51CERT2"], "SAT_AVG": "NULL", "LONGITUDE": "-71.103893", "INSTNM": "Blue Hills Regional Technical School", "LATITUDE": "42.181648", "CCSIZSET": "-2", "INSTURL": "www.bluehills.org/postgraduate-practical-nursing-program/"}, {"CITY": "Medford", "STABBR": "MA", "ADM_RATE": "NULL", "ZIP": "02155", "HIGHDEG": "1", "LOCALE": "21", "PROGRAMS": ["CIP51CERT1", "CIP12CERT1"], "SAT_AVG": "NULL", "LONGITUDE": "-71.126566", "INSTNM": "Elizabeth Grady School of Esthetics and Massage Therapy", "LATITUDE": "42.415599", "CCSIZSET": "-2", "INSTURL": "elizabethgrady.edu"}, {"CITY": "Norwood", "STABBR": "MA", "ADM_RATE": "0.8658", "ZIP": "02062-3932", "HIGHDEG": "3", "LOCALE": "21", "PROGRAMS": ["CIP11ASSOC", "CIP10BACHL", "CIP15ASSOC", "CIP11BACHL", "CIP15BACHL"], "SAT_AVG": "NULL", "LONGITUDE": "-71.188334", "INSTNM": "ITT Technical Institute-Norwood", "LATITUDE": "42.200054", "CCSIZSET": "6", "INSTURL": "www.itt-tech.edu"}, {"CITY": "Andover", "STABBR": "MA", "ADM_RATE": "NULL", "ZIP": "01810", "HIGHDEG": "4", "LOCALE": "21", "PROGRAMS": [], "SAT_AVG": "NULL", "LONGITUDE": "-71.20203", "INSTNM": "Massachusetts School of Law", "LATITUDE": "42.688042", "CCSIZSET": "18", "INSTURL": "www.mslaw.edu"}, {"CITY": "Malden", "STABBR": "MA", "ADM_RATE": "NULL", "ZIP": "02148", "HIGHDEG": "1", "LOCALE": "21", "PROGRAMS": ["CIP12CERT2", "CIP12CERT1"], "SAT_AVG": "NULL", "LONGITUDE": "-71.066818", "INSTNM": "New England Hair Academy", "LATITUDE": "42.427591", "CCSIZSET": "-2", "INSTURL": "www.newenglandhairacademy.com"}, {"CITY": "Worcester", "STABBR": "MA", "ADM_RATE": "NULL", "ZIP": "01609", "HIGHDEG": "1", "LOCALE": "12", "PROGRAMS": ["CIP12CERT2", "CIP12CERT1"], "SAT_AVG": "NULL", "LONGITUDE": "-71.807605", "INSTNM": "Rob Roy Academy-Worcester", "LATITUDE": "42.263846", "CCSIZSET": "-2", "INSTURL": "www.rob-roy.com"}, {"CITY": "Bourne", "STABBR": "MA", "ADM_RATE": "0.7931", "ZIP": "02532", "HIGHDEG": "1", "LOCALE": "22", "PROGRAMS": ["CIP51CERT2"], "SAT_AVG": "NULL", "LONGITUDE": "-70.5953", "INSTNM": "Upper Cape Cod Regional Technical School", "LATITUDE": "41.680209", "CCSIZSET": "-2", "INSTURL": "www.uppercapetech.com"}, {"CITY": "Tyngsboro", "STABBR": "MA", "ADM_RATE": "1", "ZIP": "01879", "HIGHDEG": "1", "LOCALE": "21", "PROGRAMS": ["CIP51CERT2"], "SAT_AVG": "NULL", "LONGITUDE": "-71.38618", "INSTNM": "Greater Lowell Technical School", "LATITUDE": "42.653917", "CCSIZSET": "-2", "INSTURL": "www.gltech.org"}, {"CITY": "Tewksbury", "STABBR": "MA", "ADM_RATE": "NULL", "ZIP": "01876", "HIGHDEG": "1", "LOCALE": "21", "PROGRAMS": ["CIP51CERT2"], "SAT_AVG": "NULL", "LONGITUDE": "-71.286844", "INSTNM": "The Salter School-Tewksbury Campus", "LATITUDE": "42.611476", "CCSIZSET": "-2", "INSTURL": "salterschool.com"}, {"CITY": "Malden", "STABBR": "MA", "ADM_RATE": "NULL", "ZIP": "02148", "HIGHDEG": "1", "LOCALE": "21", "PROGRAMS": ["CIP12CERT2"], "SAT_AVG": "NULL", "LONGITUDE": "-71.076619", "INSTNM": "Empire Beauty School-Malden", "LATITUDE": "42.427368", "CCSIZSET": "-2", "INSTURL": "www.empire.edu"}, {"CITY": "Tewksbury", "STABBR": "MA", "ADM_RATE": "NULL", "ZIP": "01876", "HIGHDEG": "1", "LOCALE": "21", "PROGRAMS": ["CIP12CERT2", "CIP12CERT1"], "SAT_AVG": "NULL", "LONGITUDE": "-71.220396", "INSTNM": "EINE Inc", "LATITUDE": "42.598033", "CCSIZSET": "-2", "INSTURL": "electrologyinstitute.com"}, {"CITY": "Billerica", "STABBR": "MA", "ADM_RATE": "1", "ZIP": "01821-5499", "HIGHDEG": "1", "LOCALE": "21", "PROGRAMS": ["CIP51CERT2"], "SAT_AVG": "NULL", "LONGITUDE": "-71.217926", "INSTNM": "Shawsheen Valley School of Practical Nursing", "LATITUDE": "42.546696", "CCSIZSET": "-2", "INSTURL": "www.shawsheen.tec.ma.us"}, {"CITY": "Seekonk", "STABBR": "MA", "ADM_RATE": "0.9394", "ZIP": "02771", "HIGHDEG": "1", "LOCALE": "21", "PROGRAMS": ["CIP51CERT2", "CIP31CERT2", "CIP46CERT1", "CIP47CERT1", "CIP47CERT2"], "SAT_AVG": "NULL", "LONGITUDE": "-71.324714", "INSTNM": "Motoring Technical Training Institute", "LATITUDE": "41.792171", "CCSIZSET": "-2", "INSTURL": "www.mtti.edu"}, {"CITY": "North Adams", "STABBR": "MA", "ADM_RATE": "NULL", "ZIP": "01247-3999", "HIGHDEG": "1", "LOCALE": "23", "PROGRAMS": ["CIP51CERT2", "CIP12CERT2"], "SAT_AVG": "NULL", "LONGITUDE": "-73.105953", "INSTNM": "Charles H McCann Technical School", "LATITUDE": "42.665155", "CCSIZSET": "-2", "INSTURL": "www.mccanntech.org"}, {"CITY": "Brockton", "STABBR": "MA", "ADM_RATE": "NULL", "ZIP": "02301-5734", "HIGHDEG": "1", "LOCALE": "21", "PROGRAMS": ["CIP12CERT2"], "SAT_AVG": "NULL", "LONGITUDE": "-71.043484", "INSTNM": "Ailano School of Cosmetology", "LATITUDE": "42.071117", "CCSIZSET": "-2", "INSTURL": "www.theailanoschool.com"}, {"CITY": "Brockton", "STABBR": "MA", "ADM_RATE": "NULL", "ZIP": "02301-1818", "HIGHDEG": "1", "LOCALE": "21", "PROGRAMS": ["CIP11CERT2", "CIP51CERT2", "CIP51CERT1"], "SAT_AVG": "NULL", "LONGITUDE": "-71.054643", "INSTNM": "Lincoln Technical Institute-Brockton", "LATITUDE": "42.097151", "CCSIZSET": "-2", "INSTURL": "www.lincolnedu.com/campus/brockton-ma"}, {"CITY": "Pittsfield", "STABBR": "MA", "ADM_RATE": "NULL", "ZIP": "01201-5300", "HIGHDEG": "1", "LOCALE": "13", "PROGRAMS": ["CIP13CERT2", "CIP51CERT2", "CIP43CERT2", "CIP12CERT2", "CIP22CERT2", "CIP52CERT2"], "SAT_AVG": "NULL", "LONGITUDE": "-73.256461", "INSTNM": "Mildred Elley-Pittsfield Campus", "LATITUDE": "42.4491", "CCSIZSET": "-2", "INSTURL": "www.mildred-elley.edu"}, {"CITY": "Boston", "STABBR": "MA", "ADM_RATE": "NULL", "ZIP": "02111-1093", "HIGHDEG": "2", "LOCALE": "11", "PROGRAMS": ["CIP13ASSOC", "CIP24CERT2", "CIP13CERT2", "CIP24ASSOC", "CIP44CERT2", "CIP44ASSOC"], "SAT_AVG": "NULL", "LONGITUDE": "-71.064378", "INSTNM": "Urban College of Boston", "LATITUDE": "42.352944", "CCSIZSET": "1", "INSTURL": "www.urbancollege.edu"}, {"CITY": "Ludlow", "STABBR": "MA", "ADM_RATE": "NULL", "ZIP": "01056", "HIGHDEG": "1", "LOCALE": "21", "PROGRAMS": ["CIP12CERT2", "CIP12CERT1"], "SAT_AVG": "NULL", "LONGITUDE": "-72.481367", "INSTNM": "Jolie Hair and Beauty Academy-Ludlow", "LATITUDE": "42.170121", "CCSIZSET": "-2", "INSTURL": "JolieAcademy.com"}, {"CITY": "Boston", "STABBR": "MA", "ADM_RATE": "NULL", "ZIP": "02114-2696", "HIGHDEG": "4", "LOCALE": "11", "PROGRAMS": [], "SAT_AVG": "NULL", "LONGITUDE": "-71.068939", "INSTNM": "Massachusetts General Hospital Dietetic Internship", "LATITUDE": "42.362612", "CCSIZSET": "-2", "INSTURL": "www.massgeneral.org/dietetic/"}, {"CITY": "Fitchburg", "STABBR": "MA", "ADM_RATE": "NULL", "ZIP": "01420", "HIGHDEG": "1", "LOCALE": "22", "PROGRAMS": ["CIP51CERT2"], "SAT_AVG": "NULL", "LONGITUDE": "-71.860828", "INSTNM": "Monty Tech", "LATITUDE": "42.560657", "CCSIZSET": "-2", "INSTURL": "www.montytech.net"}, {"CITY": "Worcester", "STABBR": "MA", "ADM_RATE": "NULL", "ZIP": "01605-2213", "HIGHDEG": "1", "LOCALE": "12", "PROGRAMS": ["CIP12CERT2"], "SAT_AVG": "NULL", "LONGITUDE": "-71.808651", "INSTNM": "Toni & Guy Hairdressing Academy-Worcester", "LATITUDE": "42.28463", "CCSIZSET": "-2", "INSTURL": "toniguy.edu"}, {"CITY": "Norwood", "STABBR": "MA", "ADM_RATE": "NULL", "ZIP": "02062", "HIGHDEG": "2", "LOCALE": "21", "PROGRAMS": [], "SAT_AVG": "NULL", "LONGITUDE": "-71.19308", "INSTNM": "FINE Mortuary College", "LATITUDE": "42.180896", "CCSIZSET": "1", "INSTURL": "www.FMC.EDU"}, {"CITY": "Springfield", "STABBR": "MA", "ADM_RATE": "NULL", "ZIP": "01104", "HIGHDEG": "1", "LOCALE": "12", "PROGRAMS": ["CIP11CERT2", "CIP15CERT2", "CIP51CERT2", "CIP31CERT2", "CIP47CERT2", "CIP12CERT2"], "SAT_AVG": "NULL", "LONGITUDE": "-72.543347", "INSTNM": "Branford Hall Career Institute-Springfield Campus", "LATITUDE": "42.140969", "CCSIZSET": "-2", "INSTURL": "www.branfordhall.edu"}, {"CITY": "Wilmington", "STABBR": "MA", "ADM_RATE": "0.8333", "ZIP": "01887", "HIGHDEG": "3", "LOCALE": "21", "PROGRAMS": ["CIP11ASSOC", "CIP10BACHL", "CIP15ASSOC", "CIP11BACHL", "CIP15BACHL"], "SAT_AVG": "NULL", "LONGITUDE": "-71.158041", "INSTNM": "ITT Technical Institute-Wilmington", "LATITUDE": "42.5875", "CCSIZSET": "6", "INSTURL": "www.itt-tech.edu"}, {"CITY": "Braintree", "STABBR": "MA", "ADM_RATE": "NULL", "ZIP": "02184-1744", "HIGHDEG": "4", "LOCALE": "21", "PROGRAMS": [], "SAT_AVG": "NULL", "LONGITUDE": "-71.032471", "INSTNM": "University of Phoenix-Massachusetts", "LATITUDE": "42.22717", "CCSIZSET": "6", "INSTURL": "www.phoenix.edu"}, {"CITY": "Lowell", "STABBR": "MA", "ADM_RATE": "NULL", "ZIP": "01852", "HIGHDEG": "1", "LOCALE": "21", "PROGRAMS": ["CIP11CERT2", "CIP51CERT2", "CIP51CERT1"], "SAT_AVG": "NULL", "LONGITUDE": "-71.318316", "INSTNM": "Lincoln Technical Institute-Lowell", "LATITUDE": "42.620987", "CCSIZSET": "-2", "INSTURL": "www.lincolnedu.com/campus/lowell-ma"}, {"CITY": "Falmouth", "STABBR": "MA", "ADM_RATE": "NULL", "ZIP": "02540-2958", "HIGHDEG": "4", "LOCALE": "22", "PROGRAMS": [], "SAT_AVG": "NULL", "LONGITUDE": "-70.613737", "INSTNM": "National Graduate School of Quality Management", "LATITUDE": "41.561834", "CCSIZSET": "6", "INSTURL": "www.ngs.edu"}, {"CITY": "Needham", "STABBR": "MA", "ADM_RATE": "0.1098", "ZIP": "02492-1200", "HIGHDEG": "3", "LOCALE": "21", "PROGRAMS": ["CIP14BACHL"], "SAT_AVG": "1506", "LONGITUDE": "-71.264047", "INSTNM": "Franklin W Olin College of Engineering", "LATITUDE": "42.292842", "CCSIZSET": "8", "INSTURL": "www.olin.edu"}, {"CITY": "Malden", "STABBR": "MA", "ADM_RATE": "NULL", "ZIP": "02148", "HIGHDEG": "1", "LOCALE": "21", "PROGRAMS": ["CIP51CERT2"], "SAT_AVG": "NULL", "LONGITUDE": "-71.073631", "INSTNM": "The Salter School-Malden Campus", "LATITUDE": "42.427603", "CCSIZSET": "-2", "INSTURL": "www.salterschool.com"}, {"CITY": "Framingham", "STABBR": "MA", "ADM_RATE": "NULL", "ZIP": "01702", "HIGHDEG": "1", "LOCALE": "13", "PROGRAMS": ["CIP12CERT2"], "SAT_AVG": "NULL", "LONGITUDE": "-71.423185", "INSTNM": "Empire Beauty School-Framingham", "LATITUDE": "42.297796", "CCSIZSET": "-2", "INSTURL": "www.empire.edu"}, {"CITY": "Malden", "STABBR": "MA", "ADM_RATE": "1", "ZIP": "02148-8143", "HIGHDEG": "1", "LOCALE": "21", "PROGRAMS": ["CIP51CERT2", "CIP51CERT1"], "SAT_AVG": "NULL", "LONGITUDE": "-71.078341", "INSTNM": "Medical Professional Institute", "LATITUDE": "42.426704", "CCSIZSET": "-2", "INSTURL": "www.mpi.edu"}, {"CITY": "Ipswich", "STABBR": "MA", "ADM_RATE": "NULL", "ZIP": "01938", "HIGHDEG": "1", "LOCALE": "21", "PROGRAMS": ["CIP51CERT1", "CIP12CERT1"], "SAT_AVG": "NULL", "LONGITUDE": "-70.849391", "INSTNM": "Spa Tech Institute-Ipswich", "LATITUDE": "42.688622", "CCSIZSET": "-2", "INSTURL": "www.spatech.edu"}, {"CITY": "Westboro", "STABBR": "MA", "ADM_RATE": "NULL", "ZIP": "01581", "HIGHDEG": "1", "LOCALE": "21", "PROGRAMS": ["CIP51CERT1", "CIP12CERT1"], "SAT_AVG": "NULL", "LONGITUDE": "-71.635686", "INSTNM": "Spa Tech Institute-Westboro", "LATITUDE": "42.285984", "CCSIZSET": "-2", "INSTURL": "www.spatech.edu"}, {"CITY": "Plymouth", "STABBR": "MA", "ADM_RATE": "NULL", "ZIP": "02360", "HIGHDEG": "1", "LOCALE": "21", "PROGRAMS": ["CIP51CERT1", "CIP12CERT1"], "SAT_AVG": "NULL", "LONGITUDE": "-70.704511", "INSTNM": "Spa Tech Institute-Plymouth", "LATITUDE": "41.958456", "CCSIZSET": "-2", "INSTURL": "www.spatech.edu"}, {"CITY": "Norwood", "STABBR": "MA", "ADM_RATE": "NULL", "ZIP": "02062", "HIGHDEG": "1", "LOCALE": "21", "PROGRAMS": ["CIP47CERT4", "CIP47CERT2"], "SAT_AVG": "NULL", "LONGITUDE": "-71.201408", "INSTNM": "Universal Technical Institute of Massachusetts Inc", "LATITUDE": "42.207644", "CCSIZSET": "-2", "INSTURL": "www.uti.edu/"}, {"CITY": "Fall River", "STABBR": "MA", "ADM_RATE": "NULL", "ZIP": "02720", "HIGHDEG": "1", "LOCALE": "21", "PROGRAMS": ["CIP51CERT1"], "SAT_AVG": "NULL", "LONGITUDE": "-71.153315", "INSTNM": "Salter School-Fall River", "LATITUDE": "41.69847", "CCSIZSET": "-2", "INSTURL": "www.salterschool.com/Locations/Fall-River-Campus/80/"}, {"CITY": "West Springfield", "STABBR": "MA", "ADM_RATE": "NULL", "ZIP": "01089", "HIGHDEG": "1", "LOCALE": "21", "PROGRAMS": ["CIP12CERT2"], "SAT_AVG": "NULL", "LONGITUDE": "-72.630273", "INSTNM": "DiGrigoli School of Cosmetology", "LATITUDE": "42.14632", "CCSIZSET": "-2", "INSTURL": "www.digrigoli.com"}, {"CITY": "Woburn", "STABBR": "MA", "ADM_RATE": "NULL", "ZIP": "01801", "HIGHDEG": "1", "LOCALE": "21", "PROGRAMS": ["CIP11CERT1", "CIP51CERT1", "CIP52CERT1"], "SAT_AVG": "NULL", "LONGITUDE": "-71.127076", "INSTNM": "Millennium Training Institute", "LATITUDE": "42.495839", "CCSIZSET": "-2", "INSTURL": "www.millennium.edu"}, {"CITY": "Cambridge", "STABBR": "MA", "ADM_RATE": "NULL", "ZIP": "02142", "HIGHDEG": "2", "LOCALE": "12", "PROGRAMS": ["CIP12CERT1", "CIP12ASSOC"], "SAT_AVG": "NULL", "LONGITUDE": "-71.078675", "INSTNM": "Le Cordon Bleu College of Culinary Arts-Cambridge", "LATITUDE": "42.364249", "CCSIZSET": "1", "INSTURL": "www.chefs.edu/boston"}, {"CITY": "Upton", "STABBR": "MA", "ADM_RATE": "NULL", "ZIP": "01568", "HIGHDEG": "1", "LOCALE": "21", "PROGRAMS": ["CIP51CERT2"], "SAT_AVG": "NULL", "LONGITUDE": "-71.614344", "INSTNM": "Blackstone Valley Vocational Regional School District", "LATITUDE": "42.164477", "CCSIZSET": "-2", "INSTURL": "www.valleytech.k12.ma.us"}, {"CITY": "Charlton", "STABBR": "MA", "ADM_RATE": "NULL", "ZIP": "01507-1331", "HIGHDEG": "1", "LOCALE": "41", "PROGRAMS": ["CIP51CERT2", "CIP12CERT2"], "SAT_AVG": "NULL", "LONGITUDE": "-71.956311", "INSTNM": "Southern Worcester County Regional Voc School District", "LATITUDE": "42.13549", "CCSIZSET": "-2", "INSTURL": "www.baypath.net"}, {"CITY": "Franklin", "STABBR": "MA", "ADM_RATE": "NULL", "ZIP": "02038", "HIGHDEG": "1", "LOCALE": "21", "PROGRAMS": ["CIP51CERT2", "CIP12CERT2"], "SAT_AVG": "NULL", "LONGITUDE": "-71.421481", "INSTNM": "Tri County Regional Vocational Technical High School", "LATITUDE": "42.09362", "CCSIZSET": "-2", "INSTURL": "www.tri-county.us"}, {"CITY": "New Bedford", "STABBR": "MA", "ADM_RATE": "NULL", "ZIP": "02745", "HIGHDEG": "1", "LOCALE": "22", "PROGRAMS": ["CIP51CERT2", "CIP22CERT2"], "SAT_AVG": "NULL", "LONGITUDE": "-70.941711", "INSTNM": "Salter School-New Bedford", "LATITUDE": "41.67489", "CCSIZSET": "-2", "INSTURL": "salterschool.com"}, {"CITY": "Chicopee", "STABBR": "MA", "ADM_RATE": "NULL", "ZIP": "01020-3744", "HIGHDEG": "2", "LOCALE": "21", "PROGRAMS": ["CIP51ASSOC", "CIP51CERT2", "CIP51CERT1", "CIP52ASSOC"], "SAT_AVG": "NULL", "LONGITUDE": "-72.527701", "INSTNM": "Salter College-Chicopee", "LATITUDE": "42.16075", "CCSIZSET": "1", "INSTURL": "www.salter.edu"}, {"CITY": "North Andover", "STABBR": "MA", "ADM_RATE": "NULL", "ZIP": "01845-1048", "HIGHDEG": "1", "LOCALE": "21", "PROGRAMS": ["CIP49CERT1", "CIP47CERT2"], "SAT_AVG": "NULL", "LONGITUDE": "-71.116861", "INSTNM": "New England Tractor Trailer Training School of Massachusetts", "LATITUDE": "42.73019", "CCSIZSET": "-2", "INSTURL": "www.nettts.com"}, {"CITY": "Springfield", "STABBR": "MA", "ADM_RATE": "NULL", "ZIP": "01109", "HIGHDEG": "4", "LOCALE": "12", "PROGRAMS": ["CIP44BACHL"], "SAT_AVG": "NULL", "LONGITUDE": "-72.557049", "INSTNM": "Springfield College-School of Professional and Continuing Studies", "LATITUDE": "42.102696", "CCSIZSET": "9", "INSTURL": "www.springfield.edu/school-of-professional-and-continuing-studies"}, {"CITY": "Fitchburg", "STABBR": "MA", "ADM_RATE": "NULL", "ZIP": "01420-0000", "HIGHDEG": "1", "LOCALE": "22", "PROGRAMS": ["CIP12CERT2"], "SAT_AVG": "NULL", "LONGITUDE": "-71.812241", "INSTNM": "Alexander Academy", "LATITUDE": "42.58544", "CCSIZSET": "-2", "INSTURL": "www.alexanderacademy.com"}, {"CITY": "Boston", "STABBR": "MA", "ADM_RATE": "NULL", "ZIP": "02115", "HIGHDEG": "4", "LOCALE": "11", "PROGRAMS": ["CIP51ASSOC", "CIP15ASSOC", "CIP24ASSOC", "CIP16BACHL", "CIP50BACHL", "CIP26BACHL", "CIP15BACHL"], "SAT_AVG": "NULL", "LONGITUDE": "-71.115961", "INSTNM": "Northeastern University Professional Advancement Network", "LATITUDE": "42.26599", "CCSIZSET": "12", "INSTURL": "www.northeastern.edu/globalnetwork"}, {"CITY": "Boston", "STABBR": "MA", "ADM_RATE": "NULL", "ZIP": "02122-2834", "HIGHDEG": "1", "LOCALE": "11", "PROGRAMS": ["CIP12CERT2", "CIP12CERT1"], "SAT_AVG": "NULL", "LONGITUDE": "-71.057305", "INSTNM": "Jupiter Beauty Academy", "LATITUDE": "42.30621", "CCSIZSET": "-2", "INSTURL": "www.jba.edu"}, {"CITY": "Boston", "STABBR": "MA", "ADM_RATE": "NULL", "ZIP": "02116-3631", "HIGHDEG": "1", "LOCALE": "11", "PROGRAMS": ["CIP31CERT1"], "SAT_AVG": "NULL", "LONGITUDE": "-71.076281", "INSTNM": "American Academy of Personal Training-Boston Campus", "LATITUDE": "42.35069", "CCSIZSET": "-2", "INSTURL": "www.aapt.edu"}, {"CITY": "Chicopee", "STABBR": "MA", "ADM_RATE": "NULL", "ZIP": "010221400", "HIGHDEG": "0", "LOCALE": "NULL", "PROGRAMS": [], "SAT_AVG": "NULL", "LONGITUDE": "NULL", "INSTNM": "Porter and Chester Institute of Chicopee", "LATITUDE": "NULL", "CCSIZSET": "NULL", "INSTURL": "www.porterchester.com"}, {"CITY": "Worcester", "STABBR": "MA", "ADM_RATE": "NULL", "ZIP": "016061400", "HIGHDEG": "0", "LOCALE": "NULL", "PROGRAMS": [], "SAT_AVG": "NULL", "LONGITUDE": "NULL", "INSTNM": "Porter and Chester Institute of Worcester", "LATITUDE": "NULL", "CCSIZSET": "NULL", "INSTURL": "www.porterchester.com"}, {"CITY": "Canton", "STABBR": "MA", "ADM_RATE": "NULL", "ZIP": "020212480", "HIGHDEG": "0", "LOCALE": "NULL", "PROGRAMS": [], "SAT_AVG": "NULL", "LONGITUDE": "NULL", "INSTNM": "Porter and Chester Institute of Canton", "LATITUDE": "NULL", "CCSIZSET": "NULL", "INSTURL": "www.porterchester.com"}, {"CITY": "Woburn", "STABBR": "MA", "ADM_RATE": "NULL", "ZIP": "018011041", "HIGHDEG": "0", "LOCALE": "NULL", "PROGRAMS": [], "SAT_AVG": "NULL", "LONGITUDE": "NULL", "INSTNM": "Porter and Chester Institute of Woburn", "LATITUDE": "NULL", "CCSIZSET": "NULL", "INSTURL": "www.porterchester.com"}, {"CITY": "Boston", "STABBR": "MA", "ADM_RATE": "NULL", "ZIP": "021251132", "HIGHDEG": "0", "LOCALE": "NULL", "PROGRAMS": [], "SAT_AVG": "NULL", "LONGITUDE": "NULL", "INSTNM": "Wentworth Institute of Technology", "LATITUDE": "NULL", "CCSIZSET": "NULL", "INSTURL": "www.wit.edu"}, {"CITY": "Dorchester", "STABBR": "MA", "ADM_RATE": "NULL", "ZIP": "021222841", "HIGHDEG": "0", "LOCALE": "NULL", "PROGRAMS": [], "SAT_AVG": "NULL", "LONGITUDE": "NULL", "INSTNM": "Wentworth Institute of Technology", "LATITUDE": "NULL", "CCSIZSET": "NULL", "INSTURL": "www.wit.edu"}, {"CITY": "Fall River", "STABBR": "MA", "ADM_RATE": "NULL", "ZIP": "027207399", "HIGHDEG": "0", "LOCALE": "NULL", "PROGRAMS": [], "SAT_AVG": "NULL", "LONGITUDE": "NULL", "INSTNM": "Wentworth Institute of Technology", "LATITUDE": "NULL", "CCSIZSET": "NULL", "INSTURL": "www.wit.edu"}, {"CITY": "Northampton", "STABBR": "MA", "ADM_RATE": "NULL", "ZIP": "01060", "HIGHDEG": "0", "LOCALE": "NULL", "PROGRAMS": [], "SAT_AVG": "NULL", "LONGITUDE": "NULL", "INSTNM": "Marinello School of Beauty-Northampton", "LATITUDE": "NULL", "CCSIZSET": "NULL", "INSTURL": "www.marinello.com"}]